[
	{"country":"eng","name":"Liverpool","id":"liverpool_fc","win":25,"draw":10,"loss":7,"for":81,"against":30,"isChampion":true},
	{"country":"eng","name":"Manchester United","id":"Manchester_United_F.C.","win":24,"draw":10,"loss":8,"for":65,"against":35},
	{"country":"eng","name":"Ipswich Town","id":"Ipswich_Town_F.C.","win":22,"draw":9,"loss":11,"for":68,"against":39},
	{"country":"eng","name":"Arsenal","id":"arsenal_fc","win":18,"draw":16,"loss":8,"for":52,"against":36},
	{"country":"eng","name":"Nottingham Forest","id":"Nottingham_Forest_F.C.","win":20,"draw":8,"loss":14,"for":63,"against":43},
	{"country":"eng","name":"Wolverhampton Wanderers","id":"Wolverhampton_Wanderers_F.C.","win":19,"draw":9,"loss":14,"for":58,"against":47},
	{"country":"eng","name":"Aston Villa","id":"Aston_Villa_F.C.","win":16,"draw":14,"loss":12,"for":51,"against":50},
	{"country":"eng","name":"Southampton","id":"Southampton_F.C.","win":18,"draw":9,"loss":15,"for":65,"against":53},
	{"country":"eng","name":"Middlesbrough","id":"Middlesbrough_F.C.","win":16,"draw":12,"loss":14,"for":50,"against":44},
	{"country":"eng","name":"West Bromwich Albion","id":"West_Bromwich_Albion_F.C.","win":11,"draw":19,"loss":12,"for":54,"against":50},
	{"country":"eng","name":"Leeds United","id":"Leeds_United_F.C.","win":13,"draw":14,"loss":15,"for":46,"against":50},
	{"country":"eng","name":"Norwich City","id":"Norwich_City_F.C.","win":13,"draw":14,"loss":15,"for":58,"against":66},
	{"country":"eng","name":"Crystal Palace","id":"Crystal_Palace_F.C.","win":12,"draw":16,"loss":14,"for":41,"against":50,"isReturning":true},
	{"country":"eng","name":"Tottenham Hotspur","id":"tottenham_hotspur_fc","win":15,"draw":10,"loss":17,"for":52,"against":62},
	{"country":"eng","name":"Coventry City","id":"Coventry_City_F.C.","win":16,"draw":7,"loss":19,"for":56,"against":66},
	{"country":"eng","name":"Brighton & Hove Albion","id":"Brighton_%26_Hove_Albion_F.C.","win":11,"draw":15,"loss":16,"for":47,"against":57,"isNew":true},
	{"country":"eng","name":"Manchester City","id":"Manchester_City_F.C.","win":12,"draw":13,"loss":17,"for":43,"against":66},
	{"country":"eng","name":"Stoke City","id":"Stoke_City_F.C.","win":13,"draw":10,"loss":19,"for":44,"against":58,"isReturning":true},
	{"country":"eng","name":"Everton","id":"Everton_F.C.","win":9,"draw":17,"loss":16,"for":43,"against":51},
	{"country":"eng","name":"Bristol City","id":"Bristol_City_F.C.","win":9,"draw":13,"loss":20,"for":37,"against":66,"isRemoved":true},
	{"country":"eng","name":"Derby County","id":"Derby_County_F.C.","win":11,"draw":8,"loss":23,"for":47,"against":67,"isRemoved":true},
	{"country":"eng","name":"Bolton Wanderers","id":"Bolton_Wanderers_F.C.","win":5,"draw":15,"loss":22,"for":38,"against":73,"isRemoved":true},
	{"country":"dnk","name":"KB","id":"kjobenhavns_boldklub","win":16,"draw":8,"loss":6,"for":59,"against":35,"isChampion":true},
	{"country":"dnk","name":"Næstved IF","id":"Næstved_Boldklub","win":18,"draw":4,"loss":8,"for":56,"against":36},
	{"country":"dnk","name":"Odense BK","id":"Odense_Boldklub","win":14,"draw":10,"loss":6,"for":45,"against":31},
	{"country":"dnk","name":"Aarhus GF","id":"Aarhus_Gymnastikforening","win":14,"draw":8,"loss":8,"for":50,"against":40},
	{"country":"dnk","name":"Ikast FS","id":"Ikast_FC","win":16,"draw":3,"loss":11,"for":43,"against":42},
	{"country":"dnk","name":"B 93","id":"Boldklubben_af_1893","win":13,"draw":8,"loss":9,"for":60,"against":40},
	{"country":"dnk","name":"B 1903","id":"Boldklubben_1903","win":13,"draw":8,"loss":9,"for":44,"against":35},
	{"country":"dnk","name":"Vejle BK","id":"Vejle_Boldklub","win":14,"draw":5,"loss":11,"for":63,"against":50},
	{"country":"dnk","name":"Køge BK","id":"Køge_Boldklub","win":12,"draw":8,"loss":10,"for":39,"against":39,"isReturning":true},
	{"country":"dnk","name":"Esbjerg fB","id":"Esbjerg_fB","win":10,"draw":10,"loss":10,"for":41,"against":35},
	{"country":"dnk","name":"Hvidovre IF","id":"Hvidovre_IF","win":11,"draw":8,"loss":11,"for":47,"against":48},
	{"country":"dnk","name":"Lyngby BK","id":"Lyngby_Boldklub","win":11,"draw":5,"loss":14,"for":52,"against":48,"isNew":true},
	{"country":"dnk","name":"Kastrup BK","id":"Kastrup_Boldklub","win":9,"draw":9,"loss":12,"for":34,"against":35},
	{"country":"dnk","name":"Fremad Amager","id":"Fremad_Amager","win":9,"draw":8,"loss":13,"for":36,"against":53,"isRemoved":true,"isReturning":true},
	{"country":"dnk","name":"BK Frem","id":"boldklubben_frem","win":4,"draw":4,"loss":22,"for":25,"against":69,"isRemoved":true},
	{"country":"dnk","name":"Aalborg BK","id":"AaB_Fodbold","win":2,"draw":2,"loss":26,"for":27,"against":85,"isRemoved":true},
	{"country":"sco","name":"Aberdeen","id":"Aberdeen_F.C.","win":19,"draw":10,"loss":7,"for":68,"against":36,"isChampion":true},
	{"country":"sco","name":"Celtic","id":"celtic_fc","win":18,"draw":11,"loss":7,"for":61,"against":38},
	{"country":"sco","name":"St Mirren","id":"St_Mirren_F.C.","win":15,"draw":12,"loss":9,"for":56,"against":49},
	{"country":"sco","name":"Dundee United","id":"Dundee_United_F.C.","win":12,"draw":13,"loss":11,"for":43,"against":30},
	{"country":"sco","name":"Rangers","id":"rangers_fc","win":15,"draw":7,"loss":14,"for":50,"against":46},
	{"country":"sco","name":"Morton","id":"Greenock_Morton_F.C.","win":14,"draw":8,"loss":14,"for":51,"against":46},
	{"country":"sco","name":"Partick Thistle","id":"Partick_Thistle_F.C.","win":11,"draw":14,"loss":11,"for":43,"against":47},
	{"country":"sco","name":"Kilmarnock","id":"Kilmarnock_F.C.","win":11,"draw":11,"loss":14,"for":36,"against":52,"isReturning":true},
	{"country":"sco","name":"Dundee","id":"Dundee_F.C.","win":10,"draw":6,"loss":20,"for":47,"against":73,"isRemoved":true,"isReturning":true},
	{"country":"sco","name":"Hibernian","id":"Hibernian_F.C.","win":6,"draw":6,"loss":24,"for":29,"against":67,"isRemoved":true},
	{"country":"nld","name":"AFC Ajax","id":"afc_ajax","win":22,"draw":6,"loss":6,"for":77,"against":41,"isChampion":true},
	{"country":"nld","name":"AZ '67","id":"AZ_Alkmaar","win":20,"draw":7,"loss":7,"for":77,"against":36},
	{"country":"nld","name":"PSV Eindhoven","id":"psv_eindhoven","win":18,"draw":8,"loss":8,"for":66,"against":37},
	{"country":"nld","name":"Feyenoord","id":"feyenoord","win":15,"draw":13,"loss":6,"for":58,"against":36},
	{"country":"nld","name":"FC Utrecht","id":"FC_Utrecht","win":14,"draw":11,"loss":9,"for":49,"against":35},
	{"country":"nld","name":"FC Twente","id":"FC_Twente","win":16,"draw":7,"loss":11,"for":49,"against":41},
	{"country":"nld","name":"Roda JC","id":"Roda_JC_Kerkrade","win":14,"draw":8,"loss":12,"for":51,"against":49},
	{"country":"nld","name":"Willem II","id":"Willem_II_(football_club)","win":11,"draw":12,"loss":11,"for":43,"against":63,"isReturning":true},
	{"country":"nld","name":"SBV Excelsior","id":"Excelsior_Rotterdam","win":10,"draw":11,"loss":13,"for":56,"against":60,"isReturning":true},
	{"country":"nld","name":"FC Den Haag","id":"ADO_Den_Haag","win":11,"draw":9,"loss":14,"for":38,"against":43},
	{"country":"nld","name":"MVV Maastricht","id":"MVV_Maastricht","win":10,"draw":11,"loss":13,"for":46,"against":53},
	{"country":"nld","name":"Go Ahead Eagles","id":"Go_Ahead_Eagles","win":12,"draw":6,"loss":16,"for":51,"against":52},
	{"country":"nld","name":"Sparta Rotterdam","id":"Sparta_Rotterdam","win":10,"draw":7,"loss":17,"for":45,"against":55},
	{"country":"nld","name":"PEC Zwolle","id":"PEC_Zwolle","win":9,"draw":9,"loss":16,"for":36,"against":47},
	{"country":"nld","name":"NEC","id":"NEC_Nijmegen","win":11,"draw":5,"loss":18,"for":33,"against":50},
	{"country":"nld","name":"NAC","id":"NAC_Breda","win":10,"draw":7,"loss":17,"for":35,"against":59},
	{"country":"nld","name":"Vitesse Arnhem","id":"SBV_Vitesse","win":6,"draw":13,"loss":15,"for":35,"against":59,"isRemoved":true},
	{"country":"nld","name":"HFC Haarlem","id":"HFC_Haarlem","win":7,"draw":10,"loss":17,"for":38,"against":67,"isRemoved":true},
	{"country":"bel","name":"Club Brugge K.V.","id":"club_brugge_kv","win":24,"draw":5,"loss":5,"for":76,"against":31,"isChampion":true},
	{"country":"bel","name":"Standard Liège","id":"standard_liege","win":20,"draw":9,"loss":5,"for":80,"against":31},
	{"country":"bel","name":"R.W.D. Molenbeek","id":"R.W.D._Molenbeek_(1909)","win":19,"draw":10,"loss":5,"for":57,"against":28},
	{"country":"bel","name":"K.S.C. Lokeren Oost-Vlaanderen","id":"K.S.C._Lokeren_Oost-Vlaanderen","win":18,"draw":6,"loss":10,"for":60,"against":28},
	{"country":"bel","name":"R.S.C. Anderlecht","id":"R.S.C._Anderlecht","win":17,"draw":7,"loss":10,"for":64,"against":34},
	{"country":"bel","name":"Lierse S.K.","id":"Lierse_S.K.","win":18,"draw":4,"loss":12,"for":72,"against":43},
	{"country":"bel","name":"K. Waterschei S.V. Thor Genk","id":"K._Waterschei_S.V._Thor_Genk","win":14,"draw":9,"loss":11,"for":50,"against":39},
	{"country":"bel","name":"FC Winterslag","id":"K.R.C._Genk","win":12,"draw":11,"loss":11,"for":35,"against":62},
	{"country":"bel","name":"R.F.C. de Liège","id":"RFC_Liège","win":12,"draw":9,"loss":13,"for":51,"against":47},
	{"country":"bel","name":"Cercle Brugge K.S.V.","id":"Cercle_Brugge_K.S.V.","win":13,"draw":6,"loss":15,"for":51,"against":60,"isReturning":true},
	{"country":"bel","name":"K.S.K. Beveren","id":"K.S.K._Beveren","win":11,"draw":10,"loss":13,"for":37,"against":45},
	{"country":"bel","name":"K.S.V. Waregem","id":"K.S.V._Waregem","win":10,"draw":11,"loss":13,"for":33,"against":42},
	{"country":"bel","name":"Royal Antwerp FC","id":"Royal_Antwerp_F.C.","win":10,"draw":8,"loss":16,"for":42,"against":49},
	{"country":"bel","name":"Beerschot","id":"K._Beerschot_V.A.C.","win":8,"draw":11,"loss":15,"for":37,"against":52},
	{"country":"bel","name":"Beringen FC","id":"K._Beringen_F.C.","win":9,"draw":8,"loss":17,"for":34,"against":51},
	{"country":"bel","name":"K Berchem Sport","id":"K._Berchem_Sport","win":7,"draw":12,"loss":15,"for":40,"against":61},
	{"country":"bel","name":"R. Charleroi S.C.","id":"Royal_Charleroi_S.C.","win":8,"draw":6,"loss":20,"for":23,"against":66,"isRemoved":true},
	{"country":"bel","name":"KSC Hasselt","id":"K.S.C._Hasselt","win":2,"draw":6,"loss":26,"for":21,"against":94,"isRemoved":true,"isNew":true},
	{"country":"ita","name":"Inter","id":"inter_milan","win":14,"draw":13,"loss":3,"for":44,"against":25,"isChampion":true},
	{"country":"ita","name":"Juventus","id":"Juventus_FC","win":16,"draw":6,"loss":8,"for":42,"against":25},
	{"country":"ita","name":"Torino","id":"Torino_FC","win":11,"draw":13,"loss":6,"for":26,"against":15},
	{"country":"ita","name":"Ascoli","id":"Ascoli_Calcio_1898_FC","win":11,"draw":12,"loss":7,"for":35,"against":28},
	{"country":"ita","name":"Fiorentina","id":"ACF_Fiorentina","win":11,"draw":11,"loss":8,"for":33,"against":27},
	{"country":"ita","name":"Roma","id":"AS_Roma","win":10,"draw":12,"loss":8,"for":34,"against":35},
	{"country":"ita","name":"Bologna","id":"Bologna_FC_1909","win":8,"draw":14,"loss":8,"for":23,"against":24},
	{"country":"ita","name":"Cagliari","id":"Cagliari_Calcio","win":8,"draw":14,"loss":8,"for":27,"against":29,"isReturning":true},
	{"country":"ita","name":"Perugia","id":"AC_Perugia_Calcio","win":9,"draw":12,"loss":9,"for":27,"against":32},
	{"country":"ita","name":"Napoli","id":"SSC_Napoli","win":7,"draw":14,"loss":9,"for":20,"against":20},
	{"country":"ita","name":"Avellino","id":"US_Avellino_1912","win":7,"draw":13,"loss":10,"for":24,"against":32},
	{"country":"ita","name":"Catanzaro","id":"US_Catanzaro_1929","win":5,"draw":14,"loss":11,"for":20,"against":34},
	{"country":"ita","name":"Udinese","id":"Udinese_Calcio","win":3,"draw":15,"loss":12,"for":24,"against":38,"isReturning":true},
	{"country":"ita","name":"Pescara","id":"Delfino_Pescara_1936","win":4,"draw":8,"loss":18,"for":18,"against":44,"isRemoved":true,"isReturning":true},
	{"country":"ita","name":"Milan","id":"AC_Milan","win":14,"draw":8,"loss":8,"for":34,"against":19,"isRemoved":true,"removedNote":"Disqualified and relegated due to the 1980 Totonero scandal"},
	{"country":"ita","name":"Lazio","id":"SS_Lazio","win":5,"draw":15,"loss":10,"for":21,"against":25,"isRemoved":true,"removedNote":"Disqualified and relegated due to the 1980 Totonero scandal"},
	{"country":"che","name":"Servette FC Genève","id":"Servette_FC","win":21,"draw":8,"loss":7,"for":79,"against":36},
	{"country":"che","name":"FC Basel","id":"FC_Basel","win":21,"draw":9,"loss":6,"for":91,"against":38,"isChampion":true},
	{"country":"che","name":"Grasshopper Club Zürich","id":"Grasshopper_Club_Zürich","win":19,"draw":11,"loss":6,"for":82,"against":32},
	{"country":"che","name":"FC Lucerne","id":"FC_Luzern","win":14,"draw":5,"loss":17,"for":48,"against":82,"isReturning":true},
	{"country":"che","name":"FC Zürich","id":"FC_Zürich","win":18,"draw":6,"loss":12,"for":73,"against":57},
	{"country":"che","name":"FC Sion","id":"FC_Sion","win":15,"draw":11,"loss":10,"for":69,"against":57},
	{"country":"che","name":"FC St. Gallen","id":"FC_St._Gallen","win":11,"draw":6,"loss":9,"for":48,"against":37},
	{"country":"che","name":"FC Chiasso","id":"FC_Chiasso","win":6,"draw":11,"loss":9,"for":27,"against":43},
	{"country":"che","name":"Lausanne Sports","id":"FC_Lausanne-Sport","win":8,"draw":6,"loss":12,"for":35,"against":38},
	{"country":"che","name":"BSC Young Boys","id":"bsc_young_boys","win":8,"draw":5,"loss":13,"for":34,"against":49},
	{"country":"che","name":"CS Chênois","id":"CS_Chênois","win":4,"draw":12,"loss":10,"for":32,"against":45},
	{"country":"che","name":"Neuchâtel Xamax","id":"Neuchâtel_Xamax_FCS","win":8,"draw":4,"loss":14,"for":33,"against":48},
	{"country":"che","name":"FC La Chaux-de-Fonds","id":"FC_La_Chaux-de-Fonds","win":5,"draw":7,"loss":14,"for":24,"against":57,"isRemoved":true,"isReturning":true},
	{"country":"che","name":"FC Lugano","id":"FC_Lugano","win":1,"draw":5,"loss":20,"for":18,"against":74,"isRemoved":true,"isReturning":true},
	{"country":"hun","name":"Budapest Honvéd","id":"Budapest_Honvéd_FC","win":19,"draw":10,"loss":5,"for":67,"against":38,"isChampion":true},
	{"country":"hun","name":"Újpesti Dózsa","id":"Újpest_FC","win":19,"draw":7,"loss":8,"for":86,"against":64},
	{"country":"hun","name":"Vasas","id":"Vasas_SC","win":17,"draw":10,"loss":7,"for":75,"against":52},
	{"country":"hun","name":"Videoton","id":"Fehérvár_FC","win":18,"draw":7,"loss":9,"for":65,"against":45},
	{"country":"hun","name":"Tatabányai Bányász","id":"Tatabányai_SC","win":14,"draw":12,"loss":8,"for":55,"against":40},
	{"country":"hun","name":"Ferencváros","id":"ferencvarosi_tc","win":14,"draw":11,"loss":9,"for":70,"against":51},
	{"country":"hun","name":"Pécsi MSC","id":"Pécsi_MFC","win":13,"draw":10,"loss":11,"for":57,"against":40},
	{"country":"hun","name":"MTK-VM","id":"mtk_budapest_fc","win":12,"draw":10,"loss":12,"for":48,"against":50},
	{"country":"hun","name":"Zalaegerszeg","id":"Zalaegerszegi_TE","win":11,"draw":12,"loss":11,"for":52,"against":56},
	{"country":"hun","name":"Dunaújvárosi Kohász","id":"Dunaújváros_FC","win":11,"draw":11,"loss":12,"for":60,"against":59},
	{"country":"hun","name":"Volán","id":"Volán_FC","win":12,"draw":9,"loss":13,"for":43,"against":57,"isReturning":true},
	{"country":"hun","name":"Diósgyőr","id":"Diósgyőri_VTK","win":12,"draw":8,"loss":14,"for":47,"against":42},
	{"country":"hun","name":"Rába ETO Győr","id":"Győri_ETO_FC","win":14,"draw":4,"loss":16,"for":59,"against":62},
	{"country":"hun","name":"Békéscsaba","id":"Békéscsaba_1912_Előre","win":10,"draw":12,"loss":12,"for":54,"against":67},
	{"country":"hun","name":"Debreceni MVSC","id":"Debreceni_VSC","win":8,"draw":14,"loss":12,"for":39,"against":45,"isReturning":true},
	{"country":"hun","name":"Székesfehérvári MÁV Előre","id":"Székesfehérvári_MÁV_Előre_SC","win":6,"draw":10,"loss":18,"for":28,"against":60,"isRemoved":true},
	{"country":"hun","name":"Salgótarján","id":"Salgótarjáni_BTC","win":5,"draw":10,"loss":19,"for":35,"against":59,"isRemoved":true},
	{"country":"hun","name":"Pécsi VSK","id":"Pécsi_Vasutas_SK","win":4,"draw":7,"loss":23,"for":25,"against":78,"isRemoved":true,"isReturning":true},
	{"country":"grc","name":"Olympiacos","id":"olympiacos_fc","win":20,"draw":7,"loss":7,"for":49,"against":21,"isChampion":true},
	{"country":"grc","name":"Aris","id":"Aris_Thessaloniki_F.C.","win":19,"draw":9,"loss":6,"for":46,"against":20},
	{"country":"grc","name":"Panathinaikos","id":"panathinaikos_fc","win":15,"draw":15,"loss":4,"for":38,"against":24},
	{"country":"grc","name":"AEK Athens","id":"AEK_Athens_F.C.","win":18,"draw":9,"loss":7,"for":64,"against":39},
	{"country":"grc","name":"PAOK","id":"PAOK_FC","win":17,"draw":7,"loss":10,"for":53,"against":33},
	{"country":"grc","name":"PAS Giannina","id":"PAS_Giannina_F.C.","win":14,"draw":9,"loss":11,"for":50,"against":44},
	{"country":"grc","name":"Ethnikos Piraeus","id":"Ethnikos_Piraeus_F.C.","win":13,"draw":10,"loss":11,"for":44,"against":31},
	{"country":"grc","name":"Iraklis","id":"Iraklis_F.C._(Thessaloniki)","win":13,"draw":8,"loss":13,"for":47,"against":36,"isRemoved":true,"removedNote":"Relegated due to Bribery allegations"},
	{"country":"grc","name":"AEL","id":"Athlitiki_Enosi_Larissa_F.C.","win":13,"draw":8,"loss":13,"for":33,"against":44},
	{"country":"grc","name":"Korinthos","id":"P.A.S._Korinthos","win":13,"draw":7,"loss":14,"for":38,"against":47,"isReturning":true},
	{"country":"grc","name":"OFI","id":"OFI_Crete_F.C.","win":11,"draw":10,"loss":13,"for":38,"against":45},
	{"country":"grc","name":"Doxa Drama","id":"Doxa_Drama_F.C.","win":9,"draw":11,"loss":14,"for":31,"against":41,"isReturning":true},
	{"country":"grc","name":"Panachaiki","id":"Panachaiki_F.C.","win":7,"draw":14,"loss":13,"for":38,"against":51},
	{"country":"grc","name":"Kastoria","id":"Kastoria_1980_F.C.","win":10,"draw":8,"loss":16,"for":34,"against":41,"deduct":-1},
	{"country":"grc","name":"Panionios","id":"Panionios_F.C.","win":9,"draw":9,"loss":16,"for":36,"against":48},
	{"country":"grc","name":"Kavala","id":"Kavala_F.C.","win":10,"draw":7,"loss":17,"for":26,"against":46},
	{"country":"grc","name":"Apollon Athens","id":"Apollon_Smyrnis_F.C.","win":5,"draw":13,"loss":16,"for":17,"against":37},
	{"country":"grc","name":"Rodos","id":"A.E._Rodos","win":5,"draw":9,"loss":20,"for":26,"against":60,"isRemoved":true},
	{"country":"lux","name":"Jeunesse Esch","id":"Jeunesse_Esch","win":16,"draw":1,"loss":5,"for":43,"against":25,"isChampion":true},
	{"country":"lux","name":"FA Red Boys Differdange","id":"fa_red_boys_differdange","win":14,"draw":4,"loss":4,"for":52,"against":21},
	{"country":"lux","name":"FC Progrès Niedercorn","id":"fc_progres_niederkorn","win":11,"draw":8,"loss":3,"for":58,"against":28},
	{"country":"lux","name":"Union Luxembourg","id":"Union_Luxembourg","win":12,"draw":5,"loss":5,"for":48,"against":29},
	{"country":"lux","name":"CS Grevenmacher","id":"CS_Grevenmacher","win":6,"draw":10,"loss":6,"for":27,"against":32},
	{"country":"lux","name":"Stade Dudelange","id":"Stade_Dudelange","win":7,"draw":5,"loss":10,"for":29,"against":33,"isReturning":true},
	{"country":"lux","name":"CA Spora Luxembourg","id":"CA_Spora_Luxembourg","win":6,"draw":7,"loss":9,"for":29,"against":33,"isReturning":true},
	{"country":"lux","name":"FC Avenir Beggen","id":"FC_Avenir_Beggen","win":7,"draw":4,"loss":11,"for":33,"against":33},
	{"country":"lux","name":"FC Aris Bonnevoie","id":"FC_Aris_Bonnevoie","win":6,"draw":6,"loss":10,"for":26,"against":36},
	{"country":"lux","name":"FC Etzella Ettelbruck","id":"FC_Etzella_Ettelbruck","win":7,"draw":3,"loss":12,"for":30,"against":44},
	{"country":"lux","name":"Chiers Rodange","id":"FC_Chiers","win":6,"draw":4,"loss":12,"for":18,"against":44,"isRemoved":true},
	{"country":"lux","name":"US Rumelange","id":"US_Rumelange","win":4,"draw":3,"loss":15,"for":21,"against":56,"isRemoved":true},
	{"country":"mlt","name":"Valletta F.C.","id":"valletta_fc","win":14,"draw":3,"loss":1,"for":59,"against":8,"isChampion":true,"isReturning":true},
	{"country":"mlt","name":"Sliema Wanderers F.C.","id":"sliema_wanderers_fc","win":13,"draw":2,"loss":3,"for":47,"against":11,"isReturning":true},
	{"country":"mlt","name":"Floriana F.C.","id":"floriana_fc","win":12,"draw":4,"loss":2,"for":35,"against":6,"isReturning":true},
	{"country":"mlt","name":"Hibernians F.C.","id":"hibernians_fc","win":11,"draw":4,"loss":3,"for":46,"against":11,"isReturning":true},
	{"country":"mlt","name":"Hamrun Spartans F.C.","id":"Ħamrun_Spartans_F.C.","win":9,"draw":2,"loss":7,"for":28,"against":24,"isReturning":true},
	{"country":"mlt","name":"Birkirkara F.C.","id":"Birkirkara_F.C.","win":6,"draw":2,"loss":10,"for":23,"against":38,"isReturning":true},
	{"country":"mlt","name":"Marsa F.C.","id":"Marsa_F.C.","win":6,"draw":1,"loss":11,"for":14,"against":40,"isReturning":true},
	{"country":"mlt","name":"Zebbug Rangers","id":"Żebbuġ_Rangers_F.C.","win":2,"draw":4,"loss":12,"for":9,"against":31,"isRemoved":true,"isReturning":true},
	{"country":"mlt","name":"Qormi F.C.","id":"Qormi_F.C.","win":3,"draw":1,"loss":14,"for":13,"against":65,"isRemoved":true,"isReturning":true},
	{"country":"mlt","name":"St. George's F.C.","id":"St._George%27s_F.C.","win":1,"draw":3,"loss":14,"for":9,"against":49,"isRemoved":true,"isReturning":true},
	{"country":"rou","name":"Universitatea Craiova","id":"CS_Universitatea_Craiova","win":17,"draw":10,"loss":7,"for":66,"against":31,"isChampion":true},
	{"country":"rou","name":"Steaua București","id":"fcsb","win":17,"draw":10,"loss":7,"for":74,"against":44},
	{"country":"rou","name":"Argeș Pitești","id":"FC_Argeș_Pitești","win":16,"draw":7,"loss":11,"for":51,"against":38},
	{"country":"rou","name":"FC Baia Mare","id":"CS_Minaur_Baia_Mare_(football)","win":18,"draw":3,"loss":13,"for":57,"against":51},
	{"country":"rou","name":"Dinamo București","id":"FC_Dinamo_București","win":14,"draw":9,"loss":11,"for":50,"against":37},
	{"country":"rou","name":"Sportul Studenţesc București","id":"FC_Sportul_Studențesc_București","win":16,"draw":5,"loss":13,"for":44,"against":34},
	{"country":"rou","name":"SC Bacău","id":"FCM_Bacău","win":12,"draw":11,"loss":11,"for":40,"against":47},
	{"country":"rou","name":"Politehnica Iași","id":"FC_Politehnica_Iași_(1945)","win":16,"draw":2,"loss":16,"for":47,"against":45},
	{"country":"rou","name":"Chimia Râmnicu Vâlcea","id":"Chimia_Râmnicu_Vâlcea","win":14,"draw":6,"loss":14,"for":42,"against":49},
	{"country":"rou","name":"Politehnica Timișoara","id":"FC_Politehnica_Timișoara","win":15,"draw":3,"loss":16,"for":47,"against":50},
	{"country":"rou","name":"Jiul Petroșani","id":"CSM_Jiul_Petroșani","win":12,"draw":9,"loss":13,"for":26,"against":39},
	{"country":"rou","name":"Universitatea Cluj","id":"FC_Universitatea_Cluj","win":14,"draw":4,"loss":16,"for":44,"against":43,"isReturning":true},
	{"country":"rou","name":"FC Scornicești","id":"FC_Olt_Scornicești","win":14,"draw":4,"loss":16,"for":46,"against":55,"isNew":true},
	{"country":"rou","name":"FCM Galați","id":"FCM_Dunărea_Galați","win":12,"draw":8,"loss":14,"for":50,"against":61,"isReturning":true},
	{"country":"rou","name":"ASA Târgu Mureș","id":"ASA_Târgu_Mureș_(1962)","win":13,"draw":5,"loss":16,"for":45,"against":46},
	{"country":"rou","name":"CS Târgoviște","id":"FCM_Târgoviște","win":12,"draw":7,"loss":15,"for":48,"against":53,"isRemoved":true},
	{"country":"rou","name":"Olimpia Satu Mare","id":"FC_Olimpia_Satu_Mare","win":11,"draw":8,"loss":15,"for":35,"against":50,"isRemoved":true},
	{"country":"rou","name":"Gloria Buzău","id":"FC_Gloria_Buzău","win":4,"draw":7,"loss":23,"for":22,"against":61,"isRemoved":true},
	{"country":"swe","name":"Halmstads BK","id":"Halmstads_BK","win":12,"draw":12,"loss":2,"for":38,"against":21,"isChampion":true},
	{"country":"swe","name":"IFK Göteborg","id":"IFK_Göteborg","win":13,"draw":9,"loss":4,"for":44,"against":24},
	{"country":"swe","name":"IF Elfsborg","id":"IF_Elfsborg","win":14,"draw":5,"loss":7,"for":35,"against":24},
	{"country":"swe","name":"Malmö FF","id":"malmo_ff","win":12,"draw":8,"loss":6,"for":30,"against":24},
	{"country":"swe","name":"IFK Norrköping","id":"IFK_Norrköping","win":11,"draw":9,"loss":6,"for":44,"against":28},
	{"country":"swe","name":"Hammarby IF","id":"Hammarby_Fotboll","win":11,"draw":6,"loss":9,"for":46,"against":36},
	{"country":"swe","name":"Östers IF","id":"Östers_IF","win":9,"draw":10,"loss":7,"for":32,"against":28},
	{"country":"swe","name":"Kalmar FF","id":"Kalmar_FF","win":8,"draw":8,"loss":10,"for":42,"against":39},
	{"country":"swe","name":"IFK Sundsvall","id":"IFK_Sundsvall","win":8,"draw":7,"loss":11,"for":31,"against":41,"isReturning":true},
	{"country":"swe","name":"Djurgårdens IF","id":"Djurgårdens_IF_Fotboll","win":7,"draw":8,"loss":11,"for":28,"against":35},
	{"country":"swe","name":"Åtvidabergs FF","id":"Åtvidabergs_FF","win":7,"draw":8,"loss":11,"for":20,"against":27},
	{"country":"swe","name":"Landskrona BoIS","id":"Landskrona_BoIS","win":8,"draw":5,"loss":13,"for":32,"against":41},
	{"country":"swe","name":"AIK","id":"AIK_Fotboll","win":5,"draw":10,"loss":11,"for":24,"against":35,"isRemoved":true},
	{"country":"swe","name":"IS Halmia","id":"IS_Halmia","win":2,"draw":5,"loss":19,"for":15,"against":58,"isRemoved":true,"isReturning":true},
	{"country":"aut","name":"FK Austria Wien","id":"fk_austria_wien","win":20,"draw":10,"loss":6,"for":84,"against":39,"isChampion":true},
	{"country":"aut","name":"VÖEST Linz","id":"VÖEST_Linz","win":17,"draw":9,"loss":10,"for":63,"against":41},
	{"country":"aut","name":"Linzer ASK","id":"LASK","win":13,"draw":17,"loss":6,"for":51,"against":34,"isReturning":true},
	{"country":"aut","name":"Grazer AK","id":"Grazer_AK","win":15,"draw":12,"loss":9,"for":45,"against":40},
	{"country":"aut","name":"SK Rapid Wien","id":"sk_rapid_wien","win":11,"draw":13,"loss":12,"for":46,"against":40},
	{"country":"aut","name":"SV Austria Salzburg","id":"FC_Red_Bull_Salzburg","win":12,"draw":8,"loss":16,"for":37,"against":61},
	{"country":"aut","name":"FC Admira/Wacker","id":"FC_Admira_Wacker_Mödling","win":9,"draw":13,"loss":14,"for":34,"against":53},
	{"country":"aut","name":"Wiener Sportclub","id":"Wiener_Sport-Club","win":9,"draw":11,"loss":16,"for":52,"against":59},
	{"country":"aut","name":"SK Sturm Graz","id":"SK_Sturm_Graz","win":8,"draw":13,"loss":15,"for":41,"against":60},
	{"country":"aut","name":"First Vienna FC","id":"First_Vienna_FC","win":10,"draw":6,"loss":20,"for":40,"against":66,"isRemoved":true},
	{"country":"isl","name":"ÍBV","id":"ÍBV_men%27s_football","win":10,"draw":4,"loss":4,"for":26,"against":13,"isChampion":true},
	{"country":"isl","name":"ÍA","id":"iprottabandalag_akraness","win":10,"draw":3,"loss":5,"for":27,"against":17},
	{"country":"isl","name":"Valur","id":"valur","win":9,"draw":5,"loss":4,"for":35,"against":22},
	{"country":"isl","name":"Keflavík","id":"Knattspyrnudeild_Keflavík","win":8,"draw":6,"loss":4,"for":26,"against":18},
	{"country":"isl","name":"KR","id":"knattspyrnufelag_reykjavikur","win":9,"draw":4,"loss":5,"for":29,"against":24,"isReturning":true},
	{"country":"isl","name":"Fram","id":"knattspyrnufelagio_fram","win":4,"draw":9,"loss":5,"for":25,"against":23},
	{"country":"isl","name":"Víkingur","id":"knattspyrnufelagio_vikingur","win":6,"draw":4,"loss":8,"for":26,"against":25},
	{"country":"isl","name":"Þróttur","id":"Knattspyrnufélagið_Þróttur","win":6,"draw":4,"loss":8,"for":27,"against":31},
	{"country":"isl","name":"KA","id":"Knattspyrnufélag_Akureyrar","win":3,"draw":6,"loss":9,"for":21,"against":35,"isRemoved":true},
	{"country":"isl","name":"Haukar","id":"Haukar_men%27s_football","win":1,"draw":3,"loss":14,"for":12,"against":46,"isRemoved":true,"isNew":true},
	{"country":"pol","name":"Szombierki Bytom","id":"Szombierki_Bytom","win":16,"draw":7,"loss":7,"for":42,"against":26,"isChampion":true},
	{"country":"pol","name":"Widzew Łódź","id":"Widzew_Łódź","win":13,"draw":10,"loss":7,"for":47,"against":39},
	{"country":"pol","name":"Śląsk Wrocław","id":"Śląsk_Wrocław","win":15,"draw":6,"loss":9,"for":40,"against":34},
	{"country":"pol","name":"Legia Warsaw","id":"Legia_Warsaw","win":14,"draw":8,"loss":8,"for":38,"against":31},
	{"country":"pol","name":"Wisła Kraków","id":"Wisła_Kraków","win":15,"draw":4,"loss":11,"for":58,"against":37},
	{"country":"pol","name":"Górnik Zabrze","id":"Górnik_Zabrze","win":10,"draw":12,"loss":8,"for":36,"against":38,"isReturning":true},
	{"country":"pol","name":"ŁKS Łódź","id":"ŁKS_Łódź","win":11,"draw":10,"loss":9,"for":38,"against":40},
	{"country":"pol","name":"Arka Gdynia","id":"Arka_Gdynia","win":13,"draw":5,"loss":12,"for":35,"against":32},
	{"country":"pol","name":"Odra Opole","id":"Odra_Opole","win":10,"draw":11,"loss":9,"for":21,"against":26},
	{"country":"pol","name":"Lech Poznań","id":"Lech_Poznań","win":12,"draw":6,"loss":12,"for":34,"against":32},
	{"country":"pol","name":"Ruch Chorzów","id":"Ruch_Chorzów","win":11,"draw":7,"loss":12,"for":44,"against":42},
	{"country":"pol","name":"Zagłębie Sosnowiec","id":"Zagłębie_Sosnowiec","win":10,"draw":7,"loss":13,"for":36,"against":33},
	{"country":"pol","name":"Stal Mielec","id":"Stal_Mielec","win":7,"draw":12,"loss":11,"for":28,"against":34},
	{"country":"pol","name":"Zawisza Bydgoszcz","id":"Zawisza_Bydgoszcz","win":8,"draw":8,"loss":14,"for":35,"against":52,"isReturning":true},
	{"country":"pol","name":"GKS Katowice","id":"GKS_Katowice","win":7,"draw":7,"loss":16,"for":32,"against":44,"isRemoved":true},
	{"country":"pol","name":"Polonia Bytom","id":"Polonia_Bytom","win":3,"draw":10,"loss":17,"for":23,"against":47,"isRemoved":true},
	{"country":"est","name":"Norma","id":"fc_norma_tallinn","win":12,"draw":6,"loss":2,"for":34,"against":16,"isChampion":true},
	{"country":"est","name":"Tallinna Dünamo","id":"Tallinna_JK_Dünamo","win":13,"draw":3,"loss":4,"for":40,"against":13},
	{"country":"est","name":"Sillamäe Kalev","id":"JK_Sillamäe_Kalev","win":10,"draw":6,"loss":4,"for":29,"against":17},
	{"country":"est","name":"Tempo","id":"Tallinna_JK_Tempo","win":7,"draw":8,"loss":5,"for":18,"against":14},
	{"country":"est","name":"Narva Baltika","id":"Narva_Baltika","win":9,"draw":3,"loss":8,"for":31,"against":24},
	{"country":"est","name":"Kohtla-Järve Keemik","id":"JHK_Kohtla-Järve_Keemik","win":7,"draw":6,"loss":7,"for":29,"against":20},
	{"country":"est","name":"Jõhvi Estonia Kaevandus","id":"Jõhvi_Estonia_Kaevandus","win":7,"draw":5,"loss":8,"for":32,"against":29},
	{"country":"est","name":"Pärnu Kalakombinaat","id":"Pärnu_Kalakombinaat","win":6,"draw":5,"loss":9,"for":25,"against":30},
	{"country":"est","name":"Tartu Katseremonditehas","id":"Tartu_Katseremonditehas","win":6,"draw":4,"loss":10,"for":32,"against":38,"isNew":true},
	{"country":"est","name":"Dvigatel","id":"Tallinna_SK_Dvigatel","win":7,"draw":2,"loss":11,"for":23,"against":42},
	{"country":"est","name":"TPI Tallinn","id":"TPI_Tallinn","win":0,"draw":4,"loss":16,"for":21,"against":71,"isRemoved":true,"isNew":true},
	{"country":"est","name":"Aseri SK","id":"Aseri_SK","win":0,"draw":0,"loss":0,"for":0,"against":0,"isRemoved":true},
	{"country":"lva","name":"Elektrons","id":"fk_alfa","win":22,"draw":3,"loss":1,"for":63,"against":14,"isChampion":true},
	{"country":"lva","name":"Energija","id":"FK_Apgaismes_tehnika","win":15,"draw":7,"loss":4,"for":48,"against":17},
	{"country":"lva","name":"Kimikis","id":"Kimikis","win":15,"draw":6,"loss":5,"for":36,"against":21},
	{"country":"lva","name":"Torpedo","id":"Torpedo_Rīga","win":13,"draw":7,"loss":6,"for":32,"against":15,"isNew":true},
	{"country":"lva","name":"Sarkanais Metalurgs","id":"fk_liepajas_metalurgs","win":10,"draw":10,"loss":6,"for":38,"against":28},
	{"country":"lva","name":"Jurnieks","id":"FK_Jūrnieks","win":11,"draw":7,"loss":8,"for":24,"against":27},
	{"country":"lva","name":"Progress","id":"Progress_Rīga","win":11,"draw":6,"loss":9,"for":51,"against":41,"isNew":true},
	{"country":"lva","name":"Metalists","id":"RAF_Jelgava","win":8,"draw":8,"loss":10,"for":30,"against":31,"isRemoved":true},
	{"country":"lva","name":"VEF","id":"FK_VEF_Rīga","win":8,"draw":6,"loss":12,"for":33,"against":35},
	{"country":"lva","name":"Radiotehnikis","id":"Radiotehnikis","win":6,"draw":9,"loss":11,"for":22,"against":27},
	{"country":"lva","name":"Celtnieks","id":"Celtnieks_Rīga","win":4,"draw":10,"loss":12,"for":27,"against":48},
	{"country":"lva","name":"Starts","id":"FK_Starts","win":4,"draw":6,"loss":16,"for":18,"against":46},
	{"country":"lva","name":"RPI","id":"RPI_Riga","win":4,"draw":6,"loss":16,"for":18,"against":47},
	{"country":"lva","name":"Gauja","id":"FK_Gauja","win":4,"draw":3,"loss":19,"for":22,"against":65,"isReturning":true},
	{"country":"nir","name":"Linfield","id":"linfield_fc","win":19,"draw":1,"loss":2,"for":59,"against":17,"isChampion":true},
	{"country":"nir","name":"Ballymena United","id":"Ballymena_United_F.C.","win":12,"draw":6,"loss":4,"for":52,"against":23},
	{"country":"nir","name":"Glentoran","id":"Glentoran_F.C.","win":10,"draw":7,"loss":5,"for":34,"against":27},
	{"country":"nir","name":"Cliftonville","id":"Cliftonville_F.C.","win":10,"draw":6,"loss":6,"for":29,"against":16},
	{"country":"nir","name":"Crusaders","id":"Crusaders_F.C.","win":11,"draw":2,"loss":9,"for":32,"against":24},
	{"country":"nir","name":"Portadown","id":"Portadown_F.C.","win":10,"draw":3,"loss":9,"for":36,"against":37},
	{"country":"nir","name":"Coleraine","id":"Coleraine_F.C.","win":9,"draw":4,"loss":9,"for":46,"against":48},
	{"country":"nir","name":"Distillery","id":"Lisburn_Distillery_F.C.","win":7,"draw":4,"loss":11,"for":22,"against":48},
	{"country":"nir","name":"Glenavon","id":"Glenavon_F.C.","win":5,"draw":6,"loss":11,"for":19,"against":30},
	{"country":"nir","name":"Bangor","id":"Bangor_F.C.","win":6,"draw":4,"loss":12,"for":27,"against":50},
	{"country":"nir","name":"Ards","id":"Ards_F.C.","win":4,"draw":5,"loss":13,"for":26,"against":39},
	{"country":"nir","name":"Larne","id":"Larne_F.C.","win":3,"draw":4,"loss":15,"for":17,"against":40},
	{"country":"irl","name":"Limerick United","id":"Limerick_F.C.","win":20,"draw":7,"loss":3,"for":67,"against":24,"isChampion":true},
	{"country":"irl","name":"Dundalk F.C.","id":"Dundalk_F.C.","win":20,"draw":6,"loss":4,"for":59,"against":13},
	{"country":"irl","name":"Athlone Town A.F.C.","id":"Athlone_Town_A.F.C.","win":16,"draw":7,"loss":7,"for":60,"against":24},
	{"country":"irl","name":"Shamrock Rovers F.C.","id":"Shamrock_Rovers_F.C.","win":14,"draw":10,"loss":6,"for":61,"against":29},
	{"country":"irl","name":"Finn Harps F.C.","id":"Finn_Harps_F.C.","win":16,"draw":6,"loss":8,"for":49,"against":33},
	{"country":"irl","name":"Bohemian F.C.","id":"Bohemian_F.C.","win":12,"draw":8,"loss":10,"for":42,"against":30},
	{"country":"irl","name":"Waterford","id":"Waterford_F.C.","win":8,"draw":15,"loss":7,"for":38,"against":33},
	{"country":"irl","name":"Sligo Rovers F.C.","id":"Sligo_Rovers_F.C.","win":11,"draw":9,"loss":10,"for":40,"against":45},
	{"country":"irl","name":"Thurles Town F.C.","id":"Thurles_Town_F.C.","win":9,"draw":10,"loss":11,"for":43,"against":48},
	{"country":"irl","name":"Drogheda United F.C.","id":"Drogheda_United_F.C.","win":6,"draw":16,"loss":8,"for":36,"against":41},
	{"country":"irl","name":"Galway Rovers","id":"Galway_United_F.C.","win":11,"draw":6,"loss":13,"for":32,"against":47},
	{"country":"irl","name":"St Patrick's Athletic F.C.","id":"St_Patrick%27s_Athletic_F.C.","win":9,"draw":9,"loss":12,"for":39,"against":46},
	{"country":"irl","name":"Home Farm F.C.","id":"Home_Farm_F.C.","win":10,"draw":5,"loss":15,"for":27,"against":42},
	{"country":"irl","name":"Cork United","id":"Albert_Rovers_F.C.","win":6,"draw":4,"loss":20,"for":22,"against":56},
	{"country":"irl","name":"University College Dublin A.F.C.","id":"University_College_Dublin_A.F.C.","win":5,"draw":4,"loss":21,"for":24,"against":75,"isNew":true},
	{"country":"irl","name":"Shelbourne F.C.","id":"Shelbourne_F.C.","win":3,"draw":6,"loss":21,"for":30,"against":83},
	{"country":"ltu","name":"Atmosfera Mazeikiai","id":"FK_Mažeikiai","win":22,"draw":6,"loss":4,"for":46,"against":15,"isChampion":true},
	{"country":"ltu","name":"Kelininkas Kaunas","id":"Kelininkas_Kaunas","win":20,"draw":9,"loss":3,"for":74,"against":35},
	{"country":"ltu","name":"Nevezis Kedainiai","id":"FK_Nevėžis","win":15,"draw":10,"loss":7,"for":49,"against":28},
	{"country":"ltu","name":"Tauras Siauliai","id":"Tauras_Siauliai","win":15,"draw":8,"loss":9,"for":47,"against":32},
	{"country":"ltu","name":"Statybininkas Siauliai","id":"FK_Kareda_Kaunas","win":13,"draw":11,"loss":8,"for":37,"against":23},
	{"country":"ltu","name":"Atletas Kaunas","id":"FK_Atletas_Kaunas","win":11,"draw":13,"loss":8,"for":33,"against":28},
	{"country":"ltu","name":"Dainava Alytus","id":"DFK_Dainava","win":12,"draw":10,"loss":10,"for":39,"against":38},
	{"country":"ltu","name":"Politechnika Kaunas","id":"Politechnika_Kaunas","win":11,"draw":10,"loss":11,"for":43,"against":42},
	{"country":"ltu","name":"Pazanga Vilnius","id":"Pazanga_Vilnius","win":10,"draw":11,"loss":11,"for":38,"against":38},
	{"country":"ltu","name":"Vienybe Ukmerge","id":"Vienybe_Ukmerge","win":10,"draw":11,"loss":11,"for":30,"against":34},
	{"country":"ltu","name":"Granitas Klaipėda","id":"FK_Atlantas","win":9,"draw":9,"loss":14,"for":43,"against":43},
	{"country":"ltu","name":"Utenis Utena","id":"FK_Utenis_Utena","win":9,"draw":9,"loss":14,"for":35,"against":45,"isNew":true},
	{"country":"ltu","name":"Ausra Vilnius","id":"Ausra_Vilnius","win":9,"draw":9,"loss":14,"for":22,"against":33,"isNew":true},
	{"country":"ltu","name":"Banga Kaunas","id":"FBK_Kaunas","win":9,"draw":9,"loss":14,"for":29,"against":46},
	{"country":"ltu","name":"Ekranas Panevezys","id":"FK_Ekranas","win":6,"draw":10,"loss":16,"for":29,"against":56},
	{"country":"ltu","name":"Sviesa Vilnius","id":"FC_Vilnius","win":7,"draw":7,"loss":18,"for":33,"against":52,"isRemoved":true},
	{"country":"ltu","name":"Kooperatininkas Plunge","id":"Kooperatininkas_Plunge","win":5,"draw":6,"loss":21,"for":30,"against":69,"isRemoved":true},
	{"country":"yug","name":"Red Star Belgrade","id":"red_star_belgrade","win":19,"draw":10,"loss":5,"for":54,"against":26,"isChampion":true},
	{"country":"yug","name":"Sarajevo","id":"FK_Sarajevo","win":17,"draw":7,"loss":10,"for":55,"against":41},
	{"country":"yug","name":"Radnički Niš","id":"FK_Radnički_Niš","win":14,"draw":11,"loss":9,"for":49,"against":32},
	{"country":"yug","name":"Napredak Kruševac","id":"FK_Napredak_Kruševac","win":13,"draw":13,"loss":8,"for":41,"against":27},
	{"country":"yug","name":"Hajduk Split","id":"HNK_Hajduk_Split","win":15,"draw":8,"loss":11,"for":53,"against":44},
	{"country":"yug","name":"Sloboda Tuzla","id":"FK_Sloboda_Tuzla","win":13,"draw":9,"loss":12,"for":44,"against":37},
	{"country":"yug","name":"Vardar","id":"FK_Vardar","win":10,"draw":15,"loss":9,"for":43,"against":41,"isReturning":true},
	{"country":"yug","name":"Velež","id":"FK_Velež_Mostar","win":13,"draw":8,"loss":13,"for":44,"against":39},
	{"country":"yug","name":"Željezničar","id":"FK_Željezničar_Sarajevo","win":9,"draw":15,"loss":10,"for":41,"against":47},
	{"country":"yug","name":"Rijeka","id":"HNK_Rijeka","win":12,"draw":9,"loss":13,"for":34,"against":47},
	{"country":"yug","name":"Budućnost","id":"fk_buducnost_podgorica","win":10,"draw":12,"loss":12,"for":34,"against":34},
	{"country":"yug","name":"Dinamo Zagreb","id":"gnk_dinamo_zagreb","win":9,"draw":14,"loss":11,"for":43,"against":44},
	{"country":"yug","name":"Partizan","id":"fk_partizan","win":10,"draw":12,"loss":12,"for":31,"against":37},
	{"country":"yug","name":"Borac Banja Luka","id":"FK_Borac_Banja_Luka","win":11,"draw":8,"loss":15,"for":34,"against":42},
	{"country":"yug","name":"Olimpija","id":"NK_Olimpija_Ljubljana_(1945–2005)","win":11,"draw":8,"loss":15,"for":30,"against":45},
	{"country":"yug","name":"Vojvodina","id":"FK_Vojvodina","win":12,"draw":6,"loss":16,"for":33,"against":53},
	{"country":"yug","name":"Osijek","id":"NK_Osijek","win":10,"draw":9,"loss":15,"for":28,"against":34,"isRemoved":true},
	{"country":"yug","name":"Čelik","id":"NK_Čelik_Zenica","win":5,"draw":12,"loss":17,"for":22,"against":43,"isRemoved":true,"isReturning":true},
	{"country":"bgr","name":"CSKA Sofia","id":"PFC_CSKA_Sofia","win":18,"draw":10,"loss":2,"for":60,"against":30,"isChampion":true},
	{"country":"bgr","name":"Slavia Sofia","id":"PFC_Slavia_Sofia","win":21,"draw":3,"loss":6,"for":66,"against":27},
	{"country":"bgr","name":"Levski Sofia","id":"pfc_levski_sofia","win":15,"draw":7,"loss":8,"for":45,"against":38},
	{"country":"bgr","name":"Beroe Stara Zagora","id":"PFC_Beroe_Stara_Zagora","win":13,"draw":8,"loss":9,"for":49,"against":37},
	{"country":"bgr","name":"Trakia Plovdiv","id":"Botev_Plovdiv","win":14,"draw":5,"loss":11,"for":39,"against":38},
	{"country":"bgr","name":"Marek Dupnitsa","id":"FC_Marek_Dupnitsa","win":11,"draw":9,"loss":10,"for":51,"against":42},
	{"country":"bgr","name":"Cherno More Varna","id":"PFC_Cherno_More_Varna","win":9,"draw":13,"loss":8,"for":36,"against":33},
	{"country":"bgr","name":"Minyor Pernik","id":"FC_Minyor_Pernik","win":11,"draw":6,"loss":13,"for":31,"against":46,"isReturning":true},
	{"country":"bgr","name":"Chernomorets Burgas","id":"FC_Chernomorets_Burgas","win":12,"draw":3,"loss":15,"for":39,"against":42},
	{"country":"bgr","name":"Botev Vratsa","id":"POFC_Botev_Vratsa","win":10,"draw":6,"loss":14,"for":35,"against":43},
	{"country":"bgr","name":"Lokomotiv Sofia","id":"FC_Lokomotiv_1929_Sofia","win":7,"draw":12,"loss":11,"for":32,"against":43},
	{"country":"bgr","name":"Pirin Blagoevgrad","id":"OFC_Pirin_Blagoevgrad","win":9,"draw":7,"loss":14,"for":27,"against":34},
	{"country":"bgr","name":"Sliven","id":"FC_Sliven","win":8,"draw":9,"loss":13,"for":32,"against":43},
	{"country":"bgr","name":"Spartak Pleven","id":"OFC_Spartak_Pleven","win":7,"draw":10,"loss":13,"for":26,"against":39},
	{"country":"bgr","name":"Lokomotiv Plovdiv","id":"PFC_Lokomotiv_Plovdiv","win":6,"draw":10,"loss":14,"for":33,"against":52,"isRemoved":true},
	{"country":"bgr","name":"Etar Veliko Tarnovo","id":"FC_Etar_(Veliko_Tarnovo)","win":7,"draw":6,"loss":17,"for":31,"against":45,"isRemoved":true,"isReturning":true},
	{"country":"tur","name":"Trabzonspor","id":"Trabzonspor","win":12,"draw":15,"loss":3,"for":25,"against":11,"isChampion":true},
	{"country":"tur","name":"Fenerbahçe","id":"fenerbahce_sk","win":12,"draw":11,"loss":7,"for":31,"against":27},
	{"country":"tur","name":"Zonguldakspor","id":"Zonguldak_Kömürspor","win":9,"draw":15,"loss":6,"for":26,"against":19},
	{"country":"tur","name":"Bursaspor","id":"Bursaspor","win":12,"draw":9,"loss":9,"for":28,"against":28},
	{"country":"tur","name":"Çaykur Rizespor","id":"Çaykur_Rizespor","win":14,"draw":4,"loss":12,"for":37,"against":34,"isNew":true},
	{"country":"tur","name":"Eskişehirspor","id":"Eskişehirspor","win":8,"draw":15,"loss":7,"for":29,"against":26},
	{"country":"tur","name":"Orduspor","id":"Orduspor","win":8,"draw":14,"loss":8,"for":26,"against":32},
	{"country":"tur","name":"Adana Demirspor","id":"Adana_Demirspor","win":10,"draw":9,"loss":11,"for":26,"against":23},
	{"country":"tur","name":"Galatasaray","id":"galatasaray_sk","win":8,"draw":13,"loss":9,"for":28,"against":26},
	{"country":"tur","name":"Adanaspor","id":"Adanaspor","win":9,"draw":11,"loss":10,"for":21,"against":21},
	{"country":"tur","name":"Beşiktaş","id":"besiktas_jk","win":8,"draw":13,"loss":9,"for":25,"against":27},
	{"country":"tur","name":"Altay","id":"Altay_S.K.","win":9,"draw":10,"loss":11,"for":28,"against":27},
	{"country":"tur","name":"Gaziantepspor","id":"Gaziantepspor","win":9,"draw":10,"loss":11,"for":25,"against":24,"isNew":true},
	{"country":"tur","name":"Göztepe A.Ş.","id":"Göztepe_S.K.","win":8,"draw":11,"loss":11,"for":27,"against":33,"isRemoved":true},
	{"country":"tur","name":"Kayserispor","id":"Kayserispor","win":6,"draw":13,"loss":11,"for":19,"against":28,"isRemoved":true,"isReturning":true},
	{"country":"tur","name":"Diyarbakırspor","id":"Diyarbakırspor","win":8,"draw":7,"loss":15,"for":21,"against":36,"isRemoved":true},
	{"country":"esp","name":"Real Madrid","id":"real_madrid_cf","win":22,"draw":9,"loss":3,"for":70,"against":33,"isChampion":true},
	{"country":"esp","name":"Real Sociedad","id":"Real_Sociedad","win":19,"draw":14,"loss":1,"for":54,"against":20},
	{"country":"esp","name":"Sporting Gijón","id":"Sporting_de_Gijón","win":16,"draw":7,"loss":11,"for":47,"against":34},
	{"country":"esp","name":"Barcelona","id":"fc_barcelona","win":13,"draw":12,"loss":9,"for":42,"against":33},
	{"country":"esp","name":"Real Betis","id":"Real_Betis","win":12,"draw":12,"loss":10,"for":42,"against":40,"isReturning":true},
	{"country":"esp","name":"Valencia","id":"Valencia_CF","win":12,"draw":12,"loss":10,"for":50,"against":42},
	{"country":"esp","name":"Athletic Bilbao","id":"Athletic_Bilbao","win":15,"draw":5,"loss":14,"for":52,"against":44},
	{"country":"esp","name":"Sevilla","id":"Sevilla_FC","win":14,"draw":6,"loss":14,"for":50,"against":47},
	{"country":"esp","name":"Salamanca","id":"UD_Salamanca","win":13,"draw":8,"loss":13,"for":37,"against":37},
	{"country":"esp","name":"Almería","id":"AD_Almería","win":11,"draw":11,"loss":12,"for":41,"against":50,"isNew":true},
	{"country":"esp","name":"Zaragoza","id":"Real_Zaragoza","win":13,"draw":7,"loss":14,"for":43,"against":40},
	{"country":"esp","name":"Las Palmas","id":"UD_Las_Palmas","win":13,"draw":6,"loss":15,"for":36,"against":49},
	{"country":"esp","name":"Atlético Madrid","id":"atletico_madrid","win":10,"draw":11,"loss":13,"for":38,"against":44},
	{"country":"esp","name":"Español","id":"RCD_Espanyol","win":9,"draw":12,"loss":13,"for":28,"against":37},
	{"country":"esp","name":"Hércules","id":"Hércules_CF","win":8,"draw":12,"loss":14,"for":36,"against":39},
	{"country":"esp","name":"Rayo Vallecano","id":"Rayo_Vallecano","win":9,"draw":8,"loss":17,"for":46,"against":61,"isRemoved":true},
	{"country":"esp","name":"Burgos","id":"Burgos_CF_(1936)","win":5,"draw":10,"loss":19,"for":29,"against":61,"isRemoved":true},
	{"country":"esp","name":"Málaga","id":"CD_Málaga","win":8,"draw":6,"loss":20,"for":28,"against":58,"isRemoved":true,"deduct":-3,"deductReason":"Failure to attend a match","isReturning":true},
	{"country":"alb","name":"Dinamo Tirana","id":"FC_Dinamo_City","win":14,"draw":9,"loss":3,"for":41,"against":23,"isChampion":true},
	{"country":"alb","name":"17 Nëntori","id":"kf_tirana","win":11,"draw":10,"loss":5,"for":33,"against":27},
	{"country":"alb","name":"Vllaznia","id":"fk_vllaznia_shkoder","win":12,"draw":7,"loss":7,"for":37,"against":26},
	{"country":"alb","name":"Partizani","id":"fk_partizani_tirana","win":9,"draw":11,"loss":6,"for":41,"against":30},
	{"country":"alb","name":"Flamurtari","id":"Flamurtari_FC","win":10,"draw":9,"loss":7,"for":33,"against":25},
	{"country":"alb","name":"Skënderbeu","id":"KF_Skënderbeu_Korçë","win":9,"draw":10,"loss":7,"for":27,"against":24,"isReturning":true},
	{"country":"alb","name":"Luftëtari","id":"KF_Luftëtari","win":11,"draw":5,"loss":10,"for":39,"against":35},
	{"country":"alb","name":"Lokomotiva Durrës","id":"KF_Teuta","win":8,"draw":11,"loss":7,"for":29,"against":27},
	{"country":"alb","name":"Labinoti","id":"KF_Elbasani","win":7,"draw":13,"loss":6,"for":27,"against":25},
	{"country":"alb","name":"Besa","id":"KF_Besa_Kavajë","win":9,"draw":8,"loss":9,"for":27,"against":29},
	{"country":"alb","name":"Naftëtari","id":"KF_Naftëtari","win":9,"draw":6,"loss":11,"for":29,"against":39},
	{"country":"alb","name":"Tomori","id":"FK_Tomori_Berat","win":7,"draw":9,"loss":10,"for":31,"against":37},
	{"country":"alb","name":"Shkëndija Tiranë","id":"Shkëndija_Tiranë","win":6,"draw":7,"loss":13,"for":18,"against":30,"isRemoved":true},
	{"country":"alb","name":"Apolonia","id":"FK_Apolonia_Fier","win":0,"draw":5,"loss":21,"for":15,"against":50,"isRemoved":true,"isReturning":true},
	{"country":"fin","name":"OPS Oulu","id":"Oulun_Palloseura_(football)","win":15,"draw":11,"loss":3,"for":53,"against":25,"isChampion":true},
	{"country":"fin","name":"KuPS Kuopio","id":"kuopion_palloseura","win":17,"draw":6,"loss":6,"for":58,"against":33},
	{"country":"fin","name":"HJK Helsinki","id":"Helsingin_Jalkapalloklubi","win":14,"draw":7,"loss":8,"for":48,"against":36},
	{"country":"fin","name":"Reipas Lahti","id":"Reipas_Lahti","win":12,"draw":8,"loss":9,"for":46,"against":49},
	{"country":"fin","name":"KPT Kuopio","id":"Koparit","win":13,"draw":7,"loss":9,"for":47,"against":33},
	{"country":"fin","name":"TPS Turku","id":"Turun_Palloseura","win":9,"draw":8,"loss":12,"for":46,"against":43},
	{"country":"fin","name":"Haka Valkeakoski","id":"FC_Haka","win":11,"draw":7,"loss":11,"for":58,"against":52},
	{"country":"fin","name":"KTP Kotka","id":"Kotkan_Työväen_Palloilijat","win":9,"draw":4,"loss":16,"for":33,"against":68,"isReturning":true},
	{"country":"fin","name":"KPV Kokkola","id":"Kokkolan_Palloveikot","win":7,"draw":10,"loss":12,"for":34,"against":38},
	{"country":"fin","name":"Ilves Tampere","id":"Ilves_(football)","win":10,"draw":7,"loss":12,"for":47,"against":46,"isReturning":true},
	{"country":"fin","name":"Pyrkivä Turku","id":"Pyrkivä_Turku","win":7,"draw":9,"loss":13,"for":26,"against":39,"isRemoved":true},
	{"country":"fin","name":"MiPK Mikkeli","id":"Mikkelin_Pallo-Kissat","win":6,"draw":7,"loss":16,"for":30,"against":61,"isRemoved":true},
	{"country":"fra","name":"Nantes","id":"FC_Nantes","win":26,"draw":5,"loss":7,"for":76,"against":30,"isChampion":true},
	{"country":"fra","name":"Sochaux","id":"FC_Sochaux-Montbéliard","win":24,"draw":6,"loss":8,"for":76,"against":36},
	{"country":"fra","name":"Saint-Étienne","id":"AS_Saint-Étienne","win":23,"draw":8,"loss":7,"for":73,"against":50},
	{"country":"fra","name":"Monaco","id":"AS_Monaco_FC","win":21,"draw":8,"loss":9,"for":61,"against":30},
	{"country":"fra","name":"Strasbourg","id":"RC_Strasbourg_Alsace","win":17,"draw":9,"loss":12,"for":58,"against":50},
	{"country":"fra","name":"Bordeaux","id":"FC_Girondins_de_Bordeaux","win":16,"draw":8,"loss":14,"for":64,"against":53},
	{"country":"fra","name":"Paris Saint-Germain","id":"paris_saint_germain_fc","win":15,"draw":10,"loss":13,"for":59,"against":52},
	{"country":"fra","name":"Valenciennes","id":"Valenciennes_FC","win":14,"draw":12,"loss":12,"for":47,"against":47},
	{"country":"fra","name":"Lens","id":"RC_Lens","win":14,"draw":10,"loss":14,"for":51,"against":51,"isReturning":true},
	{"country":"fra","name":"Nîmes","id":"Nîmes_Olympique","win":15,"draw":8,"loss":15,"for":45,"against":50},
	{"country":"fra","name":"Nancy","id":"AS_Nancy_Lorraine","win":15,"draw":7,"loss":16,"for":55,"against":61},
	{"country":"fra","name":"Laval","id":"Stade_Lavallois","win":15,"draw":5,"loss":18,"for":57,"against":55},
	{"country":"fra","name":"Lille","id":"Lille_OSC","win":12,"draw":11,"loss":15,"for":45,"against":49},
	{"country":"fra","name":"Angers","id":"Angers_SCO","win":14,"draw":7,"loss":17,"for":45,"against":55},
	{"country":"fra","name":"Nice","id":"OGC_Nice","win":13,"draw":6,"loss":19,"for":53,"against":62},
	{"country":"fra","name":"Bastia","id":"SC_Bastia","win":14,"draw":4,"loss":20,"for":39,"against":51},
	{"country":"fra","name":"Metz","id":"FC_Metz","win":12,"draw":8,"loss":18,"for":45,"against":60},
	{"country":"fra","name":"Lyon","id":"Olympique_Lyonnais","win":10,"draw":9,"loss":19,"for":43,"against":65},
	{"country":"fra","name":"Marseille","id":"Olympique_de_Marseille","win":9,"draw":6,"loss":23,"for":45,"against":78,"isRemoved":true},
	{"country":"fra","name":"Brest","id":"Stade_Brestois_29","win":4,"draw":7,"loss":27,"for":35,"against":87,"isRemoved":true,"isNew":true},
	{"country":"cyp","name":"APOEL","id":"apoel_fc","win":23,"draw":2,"loss":3,"for":72,"against":19,"isChampion":true},
	{"country":"cyp","name":"AC Omonia","id":"ac_omonia","win":21,"draw":6,"loss":1,"for":66,"against":14},
	{"country":"cyp","name":"Pezoporikos Larnaca","id":"Pezoporikos_Larnaca_FC","win":13,"draw":7,"loss":8,"for":44,"against":29},
	{"country":"cyp","name":"EPA Larnaca FC","id":"EPA_Larnaca_FC","win":10,"draw":10,"loss":8,"for":41,"against":27},
	{"country":"cyp","name":"AEL Limassol","id":"AEL_Limassol","win":14,"draw":2,"loss":12,"for":41,"against":43},
	{"country":"cyp","name":"Apollon Limassol","id":"apollon_limassol_fc","win":7,"draw":14,"loss":7,"for":36,"against":30},
	{"country":"cyp","name":"Anorthosis Famagusta FC","id":"Anorthosis_Famagusta_FC","win":9,"draw":8,"loss":11,"for":31,"against":31},
	{"country":"cyp","name":"Aris Limassol F.C.","id":"Aris_Limassol_FC","win":9,"draw":8,"loss":11,"for":37,"against":40},
	{"country":"cyp","name":"EN Paralimni","id":"Enosis_Neon_Paralimni_FC","win":8,"draw":8,"loss":12,"for":23,"against":26},
	{"country":"cyp","name":"Olympiakos Nicosia","id":"Olympiakos_Nicosia","win":8,"draw":8,"loss":12,"for":27,"against":48},
	{"country":"cyp","name":"Alki Larnaca FC","id":"Alki_Larnaca_FC","win":8,"draw":7,"loss":13,"for":27,"against":45},
	{"country":"cyp","name":"Keravnos","id":"Keravnos_Strovolou_FC","win":7,"draw":7,"loss":14,"for":35,"against":50,"isNew":true},
	{"country":"cyp","name":"Omonia Aradippou","id":"Omonia_Aradippou","win":6,"draw":9,"loss":13,"for":18,"against":35},
	{"country":"cyp","name":"APOP Paphos","id":"APOP_Paphos_FC","win":5,"draw":9,"loss":14,"for":23,"against":53,"isRemoved":true},
	{"country":"cyp","name":"Evagoras Paphos","id":"Evagoras_Paphos","win":4,"draw":11,"loss":13,"for":16,"against":47,"isRemoved":true},
	{"country":"prt","name":"Sporting CP","id":"sporting_cp","win":24,"draw":4,"loss":2,"for":67,"against":17,"isChampion":true},
	{"country":"prt","name":"Porto","id":"fc_porto","win":22,"draw":6,"loss":2,"for":59,"against":9},
	{"country":"prt","name":"Benfica","id":"sl_benfica","win":19,"draw":7,"loss":4,"for":79,"against":21},
	{"country":"prt","name":"Boavista","id":"Boavista_F.C.","win":15,"draw":7,"loss":8,"for":44,"against":30},
	{"country":"prt","name":"Belenenses","id":"C.F._Os_Belenenses","win":13,"draw":8,"loss":9,"for":33,"against":38},
	{"country":"prt","name":"Vitória de Guimarães","id":"Vitória_S.C.","win":11,"draw":10,"loss":9,"for":42,"against":38},
	{"country":"prt","name":"Espinho","id":"S.C._Espinho","win":11,"draw":6,"loss":13,"for":29,"against":42,"isReturning":true},
	{"country":"prt","name":"Portimonense","id":"Portimonense_S.C.","win":10,"draw":6,"loss":14,"for":32,"against":49,"isReturning":true},
	{"country":"prt","name":"Braga","id":"S.C._Braga","win":10,"draw":6,"loss":14,"for":34,"against":40},
	{"country":"prt","name":"Varzim","id":"Varzim_S.C.","win":8,"draw":10,"loss":12,"for":37,"against":45},
	{"country":"prt","name":"Marítimo","id":"C.S._Marítimo","win":9,"draw":8,"loss":13,"for":25,"against":37},
	{"country":"prt","name":"Vitória de Setúbal","id":"Vitória_F.C.","win":9,"draw":5,"loss":16,"for":29,"against":41},
	{"country":"prt","name":"União de Leiria","id":"U.D._Leiria","win":6,"draw":9,"loss":15,"for":26,"against":49,"isRemoved":true,"isNew":true},
	{"country":"prt","name":"Estoril","id":"G.D._Estoril_Praia","win":5,"draw":11,"loss":14,"for":18,"against":37,"isRemoved":true},
	{"country":"prt","name":"Beira-Mar","id":"S.C._Beira-Mar","win":5,"draw":10,"loss":15,"for":24,"against":46,"isRemoved":true},
	{"country":"prt","name":"Rio Ave","id":"Rio_Ave_F.C.","win":5,"draw":3,"loss":22,"for":22,"against":61,"isRemoved":true,"isNew":true},
	{"country":"nor","name":"Viking","id":"Viking_FK","win":13,"draw":6,"loss":3,"for":31,"against":16,"isChampion":true},
	{"country":"nor","name":"Moss","id":"Moss_FK","win":12,"draw":6,"loss":4,"for":41,"against":25},
	{"country":"nor","name":"Start","id":"IK_Start","win":12,"draw":3,"loss":7,"for":36,"against":21},
	{"country":"nor","name":"Bryne","id":"Bryne_FK","win":11,"draw":3,"loss":8,"for":37,"against":28},
	{"country":"nor","name":"Lillestrøm","id":"Lillestrøm_SK","win":7,"draw":9,"loss":6,"for":25,"against":23},
	{"country":"nor","name":"Rosenborg","id":"Rosenborg_BK","win":9,"draw":4,"loss":9,"for":31,"against":29,"isReturning":true},
	{"country":"nor","name":"Bodø/Glimt","id":"FK_Bodø/Glimt","win":8,"draw":5,"loss":9,"for":19,"against":26},
	{"country":"nor","name":"Vålerengen","id":"Vålerenga_Fotball","win":8,"draw":4,"loss":10,"for":33,"against":41},
	{"country":"nor","name":"Skeid","id":"Skeid_Fotball","win":7,"draw":5,"loss":10,"for":24,"against":27},
	{"country":"nor","name":"Hamarkameratene","id":"Hamarkameratene","win":7,"draw":4,"loss":11,"for":29,"against":33,"isRemoved":true,"isReturning":true},
	{"country":"nor","name":"Mjøndalen","id":"Mjøndalen_IF_Fotball","win":6,"draw":5,"loss":11,"for":28,"against":43,"isRemoved":true,"isReturning":true},
	{"country":"nor","name":"Brann","id":"SK_Brann","win":3,"draw":4,"loss":15,"for":18,"against":40,"isRemoved":true},
	{"country":"sov","name":"Spartak Moscow","id":"FC_Spartak_Moscow","win":21,"draw":10,"loss":3,"for":66,"against":25,"isChampion":true},
	{"country":"sov","name":"Shakhtar Donetsk","id":"fc_shakhtar_donetsk","win":20,"draw":8,"loss":6,"for":57,"against":33},
	{"country":"sov","name":"Dynamo Kyiv","id":"fc_dynamo_kyiv","win":21,"draw":5,"loss":8,"for":51,"against":26},
	{"country":"sov","name":"Dinamo Tbilisi","id":"FC_Dinamo_Tbilisi","win":19,"draw":12,"loss":3,"for":54,"against":27},
	{"country":"sov","name":"Dynamo Moscow","id":"FC_Dynamo_Moscow","win":17,"draw":9,"loss":8,"for":41,"against":27},
	{"country":"sov","name":"Dinamo Minsk","id":"fc_dinamo_minsk","win":15,"draw":6,"loss":13,"for":48,"against":38,"isReturning":true},
	{"country":"sov","name":"Ararat Yerevan","id":"FC_Ararat_Yerevan","win":12,"draw":13,"loss":9,"for":44,"against":32},
	{"country":"sov","name":"CSKA Moscow","id":"PFC_CSKA_Moscow","win":12,"draw":8,"loss":14,"for":46,"against":46},
	{"country":"sov","name":"Pakhtakor Tashkent","id":"Pakhtakor_FC","win":11,"draw":9,"loss":14,"for":42,"against":53},
	{"country":"sov","name":"Zenit Leningrad","id":"fc_zenit_saint_petersburg","win":11,"draw":9,"loss":14,"for":41,"against":45},
	{"country":"sov","name":"Chornomorets Odessa","id":"FC_Chornomorets_Odesa","win":10,"draw":11,"loss":13,"for":32,"against":37},
	{"country":"sov","name":"Lokomotiv Moscow","id":"FC_Lokomotiv_Moscow","win":8,"draw":12,"loss":14,"for":44,"against":57},
	{"country":"sov","name":"Kairat Alma-Ata","id":"FC_Kairat","win":8,"draw":9,"loss":17,"for":29,"against":44},
	{"country":"sov","name":"Neftchi Baku","id":"neftci_pfk","win":8,"draw":8,"loss":18,"for":29,"against":50},
	{"country":"sov","name":"SKA Rostov-on-Don","id":"FC_SKA_Rostov-on-Don","win":8,"draw":14,"loss":12,"for":37,"against":50,"isReturning":true},
	{"country":"sov","name":"Torpedo Moscow","id":"FC_Torpedo_Moscow","win":8,"draw":9,"loss":17,"for":32,"against":46},
	{"country":"sov","name":"Zaria Voroshilovgrad","id":"FC_Zorya_Luhansk","win":6,"draw":11,"loss":17,"for":41,"against":62,"isRemoved":true},
	{"country":"sov","name":"Krylya Sovetov Kuibyshev","id":"PFC_Krylia_Sovetov_Samara","win":7,"draw":5,"loss":22,"for":24,"against":60,"isRemoved":true,"isReturning":true},
	{"country":"fro","name":"ÍF Fuglafjørður","id":"Ítróttarfelag_Fuglafjarðar","win":11,"draw":3,"loss":0,"for":34,"against":9,"isChampion":true},
	{"country":"fro","name":"TB Tvøroyri","id":"tvoroyrar_boltfelag","win":11,"draw":2,"loss":1,"for":44,"against":18},
	{"country":"fro","name":"Havnar Bóltfelag","id":"havnar_boltfelag","win":8,"draw":2,"loss":4,"for":39,"against":20},
	{"country":"fro","name":"B36 Tórshavn","id":"B36_Tórshavn","win":4,"draw":4,"loss":6,"for":21,"against":30},
	{"country":"fro","name":"MB Miðvágur","id":"Miðvágs_Bóltfelag","win":3,"draw":5,"loss":6,"for":22,"against":27},
	{"country":"fro","name":"KÍ Klaksvík","id":"klaksvikar_itrottarfelag","win":3,"draw":4,"loss":7,"for":18,"against":36},
	{"country":"fro","name":"VB Vágur","id":"Vágs_Bóltfelag","win":1,"draw":6,"loss":7,"for":18,"against":33},
	{"country":"fro","name":"NSÍ Runavík","id":"NSÍ_Runavík","win":0,"draw":4,"loss":10,"for":12,"against":35,"isReturning":true,"isRemoved":true},
	{"country":"csk","name":"Baník Ostrava","id":"FC_Baník_Ostrava","win":16,"draw":9,"loss":5,"for":47,"against":23,"isChampion":true},
	{"country":"csk","name":"Zbrojovka Brno","id":"FC_Zbrojovka_Brno","win":15,"draw":6,"loss":9,"for":59,"against":39},
	{"country":"csk","name":"Bohemians Prague","id":"Bohemians_1905","win":13,"draw":8,"loss":9,"for":35,"against":35},
	{"country":"csk","name":"Dukla Prague","id":"Dukla_Prague","win":15,"draw":3,"loss":12,"for":53,"against":25},
	{"country":"csk","name":"Inter Bratislava","id":"FK_Inter_Bratislava","win":12,"draw":9,"loss":9,"for":33,"against":23},
	{"country":"csk","name":"Plastika Nitra","id":"FC_Nitra","win":14,"draw":4,"loss":12,"for":50,"against":46,"isReturning":true},
	{"country":"csk","name":"Spartak Trnava","id":"FC_Spartak_Trnava","win":11,"draw":10,"loss":9,"for":35,"against":35},
	{"country":"csk","name":"Lokomotíva Košice","id":"FC_Lokomotíva_Košice","win":12,"draw":7,"loss":11,"for":40,"against":32},
	{"country":"csk","name":"Slavia Prague","id":"sk_slavia_prague","win":12,"draw":6,"loss":12,"for":43,"against":42},
	{"country":"csk","name":"Sparta Prague","id":"ac_sparta_prague","win":10,"draw":10,"loss":10,"for":39,"against":42},
	{"country":"csk","name":"Slovan Bratislava","id":"sk_slovan_bratislava","win":11,"draw":7,"loss":12,"for":31,"against":35},
	{"country":"csk","name":"RH Cheb","id":"FK_Hvězda_Cheb","win":9,"draw":10,"loss":11,"for":36,"against":43,"isNew":true},
	{"country":"csk","name":"Košice","id":"FC_VSS_Košice","win":11,"draw":4,"loss":15,"for":35,"against":42},
	{"country":"csk","name":"Dukla Banská Bystrica","id":"FK_Dukla_Banská_Bystrica","win":11,"draw":4,"loss":15,"for":30,"against":50},
	{"country":"csk","name":"Jednota Trenčín","id":"TTS_Trenčín","win":8,"draw":4,"loss":18,"for":27,"against":63,"isRemoved":true},
	{"country":"csk","name":"Škoda Plzeň","id":"fc_viktoria_plzen","win":5,"draw":9,"loss":16,"for":25,"against":43,"isRemoved":true},
	{"country":"ede","name":"Berliner FC Dynamo","id":"berliner_fc_dynamo","win":20,"draw":3,"loss":3,"for":72,"against":16,"isChampion":true},
	{"country":"ede","name":"SG Dynamo Dresden","id":"Dynamo_Dresden","win":20,"draw":2,"loss":4,"for":65,"against":22},
	{"country":"ede","name":"FC Carl Zeiss Jena","id":"FC_Carl_Zeiss_Jena","win":13,"draw":6,"loss":7,"for":41,"against":24},
	{"country":"ede","name":"1. FC Magdeburg","id":"1._FC_Magdeburg","win":12,"draw":6,"loss":8,"for":45,"against":37},
	{"country":"ede","name":"FC Vorwärts Frankfurt","id":"1._FC_Frankfurt","win":11,"draw":8,"loss":7,"for":41,"against":40,"isReturning":true},
	{"country":"ede","name":"1. FC Lokomotive Leipzig","id":"1._FC_Lokomotive_Leipzig","win":11,"draw":7,"loss":8,"for":50,"against":34},
	{"country":"ede","name":"Hallescher FC Chemie","id":"Hallescher_FC","win":12,"draw":4,"loss":10,"for":38,"against":37},
	{"country":"ede","name":"BSG Sachsenring Zwickau","id":"FSV_Zwickau","win":9,"draw":4,"loss":13,"for":27,"against":42},
	{"country":"ede","name":"BSG Wismut Aue","id":"FC_Erzgebirge_Aue","win":8,"draw":4,"loss":14,"for":26,"against":42},
	{"country":"ede","name":"BSG Stahl Riesa","id":"BSG_Stahl_Riesa","win":5,"draw":10,"loss":11,"for":22,"against":53},
	{"country":"ede","name":"FC Karl-Marx-Stadt","id":"Chemnitzer_FC","win":6,"draw":7,"loss":13,"for":26,"against":38},
	{"country":"ede","name":"FC Rot-Weiss Erfurt","id":"FC_Rot-Weiß_Erfurt","win":6,"draw":6,"loss":14,"for":33,"against":38},
	{"country":"ede","name":"1. FC Union Berlin","id":"1._FC_Union_Berlin","win":6,"draw":4,"loss":16,"for":18,"against":44,"isRemoved":true},
	{"country":"ede","name":"BSG Chemie Leipzig","id":"FC_Sachsen_Leipzig","win":4,"draw":7,"loss":15,"for":21,"against":58,"isRemoved":true,"isReturning":true},
	{"country":"isr","name":"Maccabi Netanya","id":"Maccabi_Netanya_F.C.","win":19,"draw":8,"loss":3,"for":53,"against":23,"isChampion":true},
	{"country":"isr","name":"Hapoel Tel Aviv","id":"Hapoel_Tel_Aviv_F.C.","win":10,"draw":16,"loss":4,"for":28,"against":19},
	{"country":"isr","name":"Shimshon Tel Aviv","id":"Shimshon_Tel_Aviv_F.C.","win":11,"draw":10,"loss":9,"for":33,"against":24},
	{"country":"isr","name":"Hapoel Yehud","id":"Hapoel_Yehud_F.C.","win":10,"draw":12,"loss":8,"for":26,"against":24},
	{"country":"isr","name":"Maccabi Tel Aviv","id":"maccabi_tel_aviv_fc","win":9,"draw":14,"loss":7,"for":33,"against":35},
	{"country":"isr","name":"Bnei Yehuda","id":"Bnei_Yehuda_Tel_Aviv_F.C.","win":10,"draw":11,"loss":9,"for":33,"against":28},
	{"country":"isr","name":"Hapoel Kfar Saba","id":"Hapoel_Kfar_Saba_F.C.","win":10,"draw":11,"loss":9,"for":30,"against":26},
	{"country":"isr","name":"Maccabi Petah Tikva","id":"Maccabi_Petah_Tikva_F.C.","win":11,"draw":8,"loss":11,"for":32,"against":34},
	{"country":"isr","name":"Hapoel Petah Tikva","id":"Hapoel_Petah_Tikva_F.C.","win":8,"draw":12,"loss":10,"for":21,"against":34,"isReturning":true},
	{"country":"isr","name":"Hapoel Be'er Sheva","id":"Hapoel_Be%27er_Sheva_F.C.","win":7,"draw":13,"loss":10,"for":28,"against":27},
	{"country":"isr","name":"Maccabi Ramat Amidar","id":"Maccabi_Ramat_Amidar_F.C.","win":6,"draw":15,"loss":9,"for":21,"against":20,"isReturning":true},
	{"country":"isr","name":"Hapoel Haifa","id":"Hapoel_Haifa_F.C.","win":8,"draw":11,"loss":11,"for":22,"against":33},
	{"country":"isr","name":"Maccabi Jaffa","id":"Maccabi_Jaffa_F.C.","win":7,"draw":12,"loss":11,"for":33,"against":35},
	{"country":"isr","name":"Hakoah Ramat Gan","id":"Hakoah_Amidar_Ramat_Gan_F.C.","win":7,"draw":12,"loss":11,"for":27,"against":36,"isRemoved":true,"isReturning":true},
	{"country":"isr","name":"Beitar Tel Aviv","id":"Beitar_Tel_Aviv_F.C.","win":7,"draw":12,"loss":11,"for":27,"against":39,"isRemoved":true},
	{"country":"isr","name":"Beitar Jerusalem","id":"Beitar_Jerusalem_F.C.","win":4,"draw":15,"loss":11,"for":15,"against":25,"isRemoved":true},
	{"country":"wde","name":"Bayern Munich","id":"fc_bayern_munich","win":22,"draw":6,"loss":6,"for":84,"against":33,"isChampion":true},
	{"country":"wde","name":"Hamburger SV","id":"Hamburger_SV","win":20,"draw":8,"loss":6,"for":86,"against":35},
	{"country":"wde","name":"VfB Stuttgart","id":"VfB_Stuttgart","win":18,"draw":5,"loss":11,"for":75,"against":53},
	{"country":"wde","name":"1. FC Kaiserslautern","id":"1._FC_Kaiserslautern","win":17,"draw":7,"loss":10,"for":75,"against":53},
	{"country":"wde","name":"1. FC Köln","id":"1._FC_Köln","win":14,"draw":9,"loss":11,"for":72,"against":55},
	{"country":"wde","name":"Borussia Dortmund","id":"Borussia_Dortmund","win":14,"draw":8,"loss":12,"for":64,"against":56},
	{"country":"wde","name":"Borussia Mönchengladbach","id":"Borussia_Mönchengladbach","win":12,"draw":12,"loss":10,"for":61,"against":60},
	{"country":"wde","name":"Schalke 04","id":"FC_Schalke_04","win":12,"draw":9,"loss":13,"for":40,"against":51},
	{"country":"wde","name":"Eintracht Frankfurt","id":"Eintracht_Frankfurt","win":15,"draw":2,"loss":17,"for":65,"against":61},
	{"country":"wde","name":"VfL Bochum","id":"VfL_Bochum","win":13,"draw":6,"loss":15,"for":41,"against":44},
	{"country":"wde","name":"Fortuna Düsseldorf","id":"Fortuna_Düsseldorf","win":13,"draw":6,"loss":15,"for":62,"against":72},
	{"country":"wde","name":"Bayer Leverkusen","id":"bayer_04_leverkusen","win":12,"draw":8,"loss":14,"for":45,"against":61,"isNew":true},
	{"country":"wde","name":"1860 Munich","id":"TSV_1860_Munich","win":10,"draw":10,"loss":14,"for":42,"against":53,"isReturning":true},
	{"country":"wde","name":"MSV Duisburg","id":"MSV_Duisburg","win":11,"draw":7,"loss":16,"for":43,"against":57},
	{"country":"wde","name":"Bayer 05 Uerdingen","id":"KFC_Uerdingen_05","win":12,"draw":5,"loss":17,"for":43,"against":61,"isReturning":true},
	{"country":"wde","name":"Hertha BSC","id":"Hertha_BSC","win":11,"draw":7,"loss":16,"for":41,"against":61,"isRemoved":true},
	{"country":"wde","name":"Werder Bremen","id":"SV_Werder_Bremen","win":11,"draw":3,"loss":20,"for":52,"against":93,"isRemoved":true},
	{"country":"wde","name":"Eintracht Braunschweig","id":"Eintracht_Braunschweig","win":6,"draw":8,"loss":20,"for":32,"against":64,"isRemoved":true}
]