[
{"country":"eng","name":"Liverpool","id":"Liverpool_F.C.","win":26,"draw":9,"loss":7,"for":79,"against":34,"isChampion":true},
{"country":"eng","name":"Leeds United","id":"Leeds_United_F.C.","win":23,"draw":9,"loss":10,"for":79,"against":38},
{"country":"eng","name":"Burnley","id":"Burnley_F.C.","win":24,"draw":7,"loss":11,"for":79,"against":47},
{"country":"eng","name":"Manchester United","id":"Manchester_United_F.C.","win":18,"draw":15,"loss":9,"for":84,"against":59},
{"country":"eng","name":"Chelsea","id":"Chelsea_F.C.","win":22,"draw":7,"loss":13,"for":65,"against":53},
{"country":"eng","name":"West Bromwich Albion","id":"West_Bromwich_Albion_F.C.","win":19,"draw":12,"loss":11,"for":91,"against":69},
{"country":"eng","name":"Leicester City","id":"Leicester_City_F.C.","win":21,"draw":7,"loss":14,"for":80,"against":65},
{"country":"eng","name":"Tottenham Hotspur","id":"Tottenham_Hotspur_F.C.","win":16,"draw":12,"loss":14,"for":75,"against":66},
{"country":"eng","name":"Sheffield United","id":"Sheffield_United_F.C.","win":16,"draw":11,"loss":15,"for":56,"against":59},
{"country":"eng","name":"Stoke City","id":"Stoke_City_F.C.","win":15,"draw":12,"loss":15,"for":65,"against":64},
{"country":"eng","name":"Everton","id":"Everton_F.C.","win":15,"draw":11,"loss":16,"for":56,"against":62},
{"country":"eng","name":"West Ham United","id":"West_Ham_United_F.C.","win":15,"draw":9,"loss":18,"for":70,"against":83},
{"country":"eng","name":"Blackpool","id":"Blackpool_F.C.","win":14,"draw":9,"loss":19,"for":55,"against":65},
{"country":"eng","name":"Arsenal","id":"Arsenal_F.C.","win":12,"draw":13,"loss":17,"for":62,"against":75},
{"country":"eng","name":"Newcastle United","id":"Newcastle_United_F.C.","win":14,"draw":9,"loss":19,"for":50,"against":63,"isReturning":true},
{"country":"eng","name":"Aston Villa","id":"Aston_Villa_F.C.","win":15,"draw":6,"loss":21,"for":69,"against":80},
{"country":"eng","name":"Sheffield Wednesday","id":"Sheffield_Wednesday_F.C.","win":14,"draw":8,"loss":20,"for":56,"against":66},
{"country":"eng","name":"Nottingham Forest","id":"Nottingham_Forest_F.C.","win":14,"draw":8,"loss":20,"for":56,"against":72},
{"country":"eng","name":"Sunderland","id":"Sunderland_A.F.C.","win":14,"draw":8,"loss":20,"for":51,"against":72},
{"country":"eng","name":"Fulham","id":"Fulham_F.C.","win":14,"draw":7,"loss":21,"for":67,"against":85},
{"country":"eng","name":"Northampton Town","id":"Northampton_Town_F.C.","win":10,"draw":13,"loss":19,"for":55,"against":92,"isRemoved":true,"isNew":true},
{"country":"eng","name":"Blackburn Rovers","id":"Blackburn_Rovers_F.C.","win":8,"draw":4,"loss":30,"for":57,"against":88,"isRemoved":true}
][
{"country":"dnk","name":"Hvidovre IF","id":"Hvidovre_IF","win":11,"draw":9,"loss":2,"for":40,"against":16,"isChampion":true},
{"country":"dnk","name":"Boldklubben Frem","id":"Boldklubben_Frem","win":11,"draw":5,"loss":6,"for":33,"against":22},
{"country":"dnk","name":"Kjøbenhavns Boldklub","id":"Kjøbenhavns_Boldklub","win":10,"draw":5,"loss":7,"for":40,"against":32},
{"country":"dnk","name":"Aarhus Gymnastikforening","id":"Aarhus_Gymnastikforening","win":11,"draw":3,"loss":8,"for":45,"against":41},
{"country":"dnk","name":"Vejle Boldklub","id":"Vejle_Boldklub","win":9,"draw":5,"loss":8,"for":44,"against":41},
{"country":"dnk","name":"Akademisk Boldklub","id":"Akademisk_Boldklub","win":9,"draw":3,"loss":10,"for":35,"against":29,"isReturning":true},
{"country":"dnk","name":"Esbjerg fB","id":"Esbjerg_fB","win":8,"draw":5,"loss":9,"for":35,"against":36},
{"country":"dnk","name":"Boldklubben 1903","id":"Boldklubben_1903","win":8,"draw":5,"loss":9,"for":29,"against":33},
{"country":"dnk","name":"Aalborg Boldspilklub","id":"AaB_Fodbold","win":9,"draw":2,"loss":11,"for":32,"against":32},
{"country":"dnk","name":"Køge BK","id":"Køge_Boldklub","win":8,"draw":3,"loss":11,"for":40,"against":45,"isReturning":true},
{"country":"dnk","name":"Boldklubben 1909","id":"Boldklubben_1909","win":6,"draw":4,"loss":12,"for":35,"against":59,"isRemoved":true},
{"country":"dnk","name":"Boldklubben 1913","id":"Boldklubben_1913","win":5,"draw":5,"loss":12,"for":26,"against":48,"isRemoved":true}
][
{"country":"sco","name":"Celtic","id":"Celtic_F.C.","win":27,"draw":3,"loss":4,"for":106,"against":30,"isChampion":true},
{"country":"sco","name":"Rangers","id":"Rangers_F.C.","win":25,"draw":5,"loss":4,"for":91,"against":29},
{"country":"sco","name":"Kilmarnock","id":"Kilmarnock_F.C.","win":20,"draw":5,"loss":9,"for":73,"against":46},
{"country":"sco","name":"Dunfermline","id":"Dunfermline_Athletic_F.C.","win":19,"draw":6,"loss":9,"for":94,"against":55},
{"country":"sco","name":"Dundee United","id":"Dundee_United_F.C.","win":19,"draw":5,"loss":10,"for":79,"against":51},
{"country":"sco","name":"Hibernian","id":"Hibernian_F.C.","win":16,"draw":6,"loss":12,"for":81,"against":55},
{"country":"sco","name":"Hearts","id":"Heart_of_Midlothian_F.C.","win":13,"draw":12,"loss":9,"for":56,"against":48},
{"country":"sco","name":"Aberdeen","id":"Aberdeen_F.C.","win":15,"draw":6,"loss":13,"for":61,"against":54},
{"country":"sco","name":"Dundee","id":"Dundee_F.C.","win":14,"draw":6,"loss":14,"for":61,"against":61},
{"country":"sco","name":"Falkirk","id":"Falkirk_F.C.","win":15,"draw":1,"loss":18,"for":48,"against":72},
{"country":"sco","name":"Clyde","id":"Clyde_F.C.","win":13,"draw":4,"loss":17,"for":62,"against":64},
{"country":"sco","name":"Partick Thistle","id":"Partick_Thistle_F.C.","win":10,"draw":10,"loss":14,"for":55,"against":64},
{"country":"sco","name":"Motherwell","id":"Motherwell_F.C.","win":12,"draw":4,"loss":18,"for":52,"against":69},
{"country":"sco","name":"St Johnstone","id":"St_Johnstone_F.C.","win":9,"draw":8,"loss":17,"for":58,"against":81},
{"country":"sco","name":"Stirling Albion","id":"Stirling_Albion_F.C.","win":9,"draw":8,"loss":17,"for":40,"against":68,"isReturning":true},
{"country":"sco","name":"St Mirren","id":"St_Mirren_F.C.","win":9,"draw":4,"loss":21,"for":44,"against":82},
{"country":"sco","name":"Morton","id":"Greenock_Morton_F.C.","win":8,"draw":5,"loss":21,"for":42,"against":84,"isRemoved":true},
{"country":"sco","name":"Hamilton Academical","id":"Hamilton_Academical_F.C.","win":3,"draw":2,"loss":29,"for":27,"against":117,"isRemoved":true,"isReturning":true}
][
{"country":"nld","name":"Ajax","id":"AFC_Ajax","win":24,"draw":4,"loss":2,"for":79,"against":25,"isChampion":true},
{"country":"nld","name":"Feijenoord","id":"Feyenoord","win":21,"draw":3,"loss":6,"for":65,"against":30},
{"country":"nld","name":"ADO","id":"ADO_Den_Haag","win":15,"draw":9,"loss":6,"for":72,"against":37},
{"country":"nld","name":"DWS","id":"AFC_DWS","win":15,"draw":6,"loss":9,"for":48,"against":30},
{"country":"nld","name":"Go Ahead","id":"Go_Ahead_Eagles","win":14,"draw":8,"loss":8,"for":49,"against":33},
{"country":"nld","name":"GVAV","id":"FC_Groningen","win":12,"draw":7,"loss":11,"for":43,"against":43},
{"country":"nld","name":"Sparta Rotterdam","id":"Sparta_Rotterdam","win":12,"draw":5,"loss":13,"for":53,"against":51},
{"country":"nld","name":"PSV Eindhoven","id":"PSV_Eindhoven","win":10,"draw":8,"loss":12,"for":57,"against":53},
{"country":"nld","name":"Fortuna '54","id":"Fortuna_Sittard","win":9,"draw":8,"loss":13,"for":36,"against":54},
{"country":"nld","name":"Willem II","id":"Willem_II_(football_club)","win":11,"draw":3,"loss":16,"for":42,"against":59,"isReturning":true},
{"country":"nld","name":"FC Twente","id":"FC_Twente","win":9,"draw":6,"loss":15,"for":43,"against":61,"isNew":true},
{"country":"nld","name":"DOS","id":"DHSC_(football_club)","win":9,"draw":6,"loss":15,"for":48,"against":72},
{"country":"nld","name":"Telstar","id":"SC_Telstar","win":8,"draw":6,"loss":16,"for":39,"against":52},
{"country":"nld","name":"Elinkwijk","id":"FC_Utrecht","win":7,"draw":8,"loss":15,"for":37,"against":64,"isNew":true},
{"country":"nld","name":"MVV Maastricht","id":"MVV_Maastricht","win":6,"draw":9,"loss":15,"for":36,"against":56},
{"country":"nld","name":"Heracles","id":"Heracles_Almelo","win":5,"draw":10,"loss":15,"for":32,"against":59,"isRemoved":true}
][
{"country":"bel","name":"R.S.C. Anderlecht","id":"R.S.C._Anderlecht","win":21,"draw":5,"loss":4,"for":88,"against":18,"isChampion":true},
{"country":"bel","name":"K. Sint-Truidense V.V.","id":"Sint-Truidense_V.V.","win":18,"draw":4,"loss":8,"for":43,"against":29},
{"country":"bel","name":"Standard Liège","id":"Standard_Liège","win":16,"draw":8,"loss":6,"for":47,"against":24},
{"country":"bel","name":"Beerschot","id":"K._Beerschot_V.A.C.","win":15,"draw":9,"loss":6,"for":45,"against":29},
{"country":"bel","name":"Club Brugge K.V.","id":"Club_Brugge_KV","win":12,"draw":11,"loss":7,"for":56,"against":39},
{"country":"bel","name":"KV Mechelen","id":"K.V._Mechelen","win":13,"draw":7,"loss":10,"for":35,"against":39,"isReturning":true},
{"country":"bel","name":"La Gantoise","id":"K.A.A._Gent","win":11,"draw":8,"loss":11,"for":47,"against":62},
{"country":"bel","name":"R.F.C. Tilleur-Saint-Nicolas","id":"R.F.C._Tilleur","win":9,"draw":12,"loss":9,"for":30,"against":37},
{"country":"bel","name":"R.F.C. de Liège","id":"RFC_Liège","win":11,"draw":7,"loss":12,"for":52,"against":46},
{"country":"bel","name":"Royal Antwerp FC","id":"Royal_Antwerp_F.C.","win":11,"draw":7,"loss":12,"for":43,"against":44},
{"country":"bel","name":"Lierse S.K.","id":"Lierse_S.K.","win":8,"draw":10,"loss":12,"for":30,"against":40},
{"country":"bel","name":"Racing White","id":"R.W.D._Molenbeek_(1909)","win":8,"draw":8,"loss":14,"for":36,"against":47,"isReturning":true},
{"country":"bel","name":"Daring Club Bruxelles","id":"R._Daring_Club_Molenbeek","win":7,"draw":10,"loss":13,"for":25,"against":31},
{"country":"bel","name":"Beringen FC","id":"K._Beringen_F.C.","win":7,"draw":6,"loss":17,"for":29,"against":51},
{"country":"bel","name":"K Berchem Sport","id":"K._Berchem_Sport","win":4,"draw":10,"loss":16,"for":24,"against":52,"isRemoved":true},
{"country":"bel","name":"Cercle Brugge K.S.V.","id":"Cercle_Brugge_K.S.V.","win":5,"draw":6,"loss":19,"for":19,"against":61,"isRemoved":true}
]
[
{"country":"ita","name":"Internazionale","id":"Inter_Milan","win":20,"draw":10,"loss":4,"for":70,"against":28,"isChampion":true},
{"country":"ita","name":"Bologna","id":"Bologna_FC_1909","win":19,"draw":8,"loss":7,"for":60,"against":37},
{"country":"ita","name":"Napoli","id":"SSC_Napoli","win":17,"draw":11,"loss":6,"for":44,"against":27,"isReturning":true},
{"country":"ita","name":"Fiorentina","id":"ACF_Fiorentina","win":16,"draw":11,"loss":7,"for":45,"against":22},
{"country":"ita","name":"Juventus","id":"Juventus_FC","win":13,"draw":16,"loss":5,"for":38,"against":23},
{"country":"ita","name":"Vicenza","id":"LR_Vicenza","win":13,"draw":14,"loss":7,"for":44,"against":34},
{"country":"ita","name":"Milan","id":"AC_Milan","win":13,"draw":12,"loss":9,"for":43,"against":33},
{"country":"ita","name":"Roma","id":"AS_Roma","win":13,"draw":10,"loss":11,"for":28,"against":31},
{"country":"ita","name":"Brescia","id":"Brescia_Calcio","win":12,"draw":8,"loss":14,"for":43,"against":44,"isReturning":true},
{"country":"ita","name":"Torino","id":"Torino_FC","win":9,"draw":13,"loss":12,"for":31,"against":34},
{"country":"ita","name":"Cagliari","id":"Cagliari_Calcio","win":10,"draw":10,"loss":14,"for":36,"against":37},
{"country":"ita","name":"Foggia","id":"Calcio_Foggia_1920","win":8,"draw":13,"loss":13,"for":22,"against":30},
{"country":"ita","name":"Lazio","id":"SS_Lazio","win":8,"draw":13,"loss":13,"for":28,"against":41},
{"country":"ita","name":"Atalanta","id":"Atalanta_BC","win":9,"draw":11,"loss":14,"for":24,"against":37},
{"country":"ita","name":"SPAL","id":"SPAL","win":9,"draw":10,"loss":15,"for":38,"against":45,"isReturning":true},
{"country":"ita","name":"Sampdoria","id":"UC_Sampdoria","win":9,"draw":9,"loss":16,"for":27,"against":47,"isRemoved":true},
{"country":"ita","name":"Catania","id":"Catania_FC","win":5,"draw":12,"loss":17,"for":24,"against":56,"isRemoved":true},
{"country":"ita","name":"Varese","id":"SSD_Varese_Calcio","win":2,"draw":11,"loss":21,"for":23,"against":62,"isRemoved":true}
]
[
{"country":"che","name":"Zürich","id":"FC_Zürich","win":18,"draw":6,"loss":2,"for":73,"against":25,"isChampion":true},
{"country":"che","name":"Servette","id":"Servette_FC","win":14,"draw":7,"loss":5,"for":57,"against":45},
{"country":"che","name":"Lausanne-Sport","id":"FC_Lausanne-Sport","win":12,"draw":8,"loss":6,"for":72,"against":46},
{"country":"che","name":"La Chaux-de-Fonds","id":"FC_La_Chaux-de-Fonds","win":12,"draw":7,"loss":7,"for":53,"against":42},
{"country":"che","name":"Young Boys","id":"BSC_Young_Boys","win":11,"draw":7,"loss":8,"for":72,"against":47},
{"country":"che","name":"Basel","id":"FC_Basel","win":10,"draw":7,"loss":9,"for":64,"against":57},
{"country":"che","name":"Grasshopper Club","id":"Grasshopper_Club_Zürich","win":11,"draw":5,"loss":10,"for":55,"against":54},
{"country":"che","name":"Sion","id":"FC_Sion","win":9,"draw":8,"loss":9,"for":36,"against":36},
{"country":"che","name":"Lugano","id":"FC_Lugano","win":6,"draw":10,"loss":10,"for":27,"against":37},
{"country":"che","name":"Biel-Bienne","id":"FC_Biel-Bienne","win":6,"draw":10,"loss":10,"for":38,"against":56},
{"country":"che","name":"Grenchen","id":"FC_Grenchen","win":8,"draw":6,"loss":12,"for":42,"against":65},
{"country":"che","name":"Young Fellows Zürich","id":"SC_Young_Fellows_Juventus","win":7,"draw":7,"loss":12,"for":46,"against":62,"isReturning":true},
{"country":"che","name":"Luzern","id":"FC_Luzern","win":4,"draw":10,"loss":12,"for":36,"against":56,"isRemoved":true},
{"country":"che","name":"Urania Genève Sport","id":"Urania_Genève_Sport","win":3,"draw":4,"loss":19,"for":35,"against":78,"isRemoved":true,"isReturning":true}
]